not_gate.vhd
-- not_gate.vhd
--
-- THE DESIGN. This is the circuit itself. It has no main(), no stdin, no
-- printing. It is a description of a piece of hardware: one input wire, one
-- output wire, and an inverter between them. That is genuinely all.

library ieee;
use ieee.std_logic_1164.all;   -- gives us the std_logic type
use ieee.numeric_std.all;

entity not_gate is
  port (
    clk : in  std_logic;
    counter: out std_logic_vector(7 downto 0)
  );
end entity not_gate;

architecture rtl of not_gate is
  signal cnt: unsigned(7 downto 0) := (others => '0');

begin
  process (clk)
    begin
      if rising_edge(clk) then
        cnt <= cnt + 1;
      end if;

  end process;

  counter <= std_logic_vector(cnt);
  
end architecture rtl;

tb_not_gate.vhd
-- tb_not_gate.vhd
--
-- THE TESTBENCH. This is the part that "runs".
--
-- Note the empty port list: `entity tb_not_gate is end;`. A testbench connects
-- to nothing, because it IS the outside world. It manufactures the input
-- signals, waits, and checks what came back.
--
-- Mental model: your design is a chip on a bench, and the testbench is the
-- lab technician poking it with a signal generator.

library ieee;
use ieee.std_logic_1164.all;
use ieee.numeric_std.all;

entity tb_not_gate is
end entity tb_not_gate;

architecture sim of tb_not_gate is

  signal clk: std_logic := '0';
  signal counter : std_logic_vector(7 downto 0);

begin

  dut : entity work.not_gate
    port map (
      clk => clk,
      counter => counter 
    );

  stimulus : process
  begin
    wait for 10 ns;

    for i in 0 to 30 loop
      clk <= '1';
      wait for 10 ns;                 -- let it settle, then look
      clk <= '0';
      wait for 10 ns;                 -- let it settle, then look
    end loop;
    --
    -- ------------------------------------------------------------------------
    -- -- Hold at the end. Without this the simulation stops the instant the
    -- -- last check passes, the final state has zero width, and the waveform
    -- -- appears to just fall off the edge. Small thing, endlessly confusing
    -- -- the first time.
    -- ------------------------------------------------------------------------
    -- wait for 20 ns;
    --
    -- report "all checks passed";
    wait;                           -- stop forever; ends the simulation

  end process;


end architecture sim;

tb_not_gate.vcd
$date
  Mon Aug 24 13:13:25 2026
$end
$version
  GHDL v0
$end
$timescale
  1 fs
$end
$scope module standard $end
$upscope $end
$scope module textio $end
$upscope $end
$scope module std_logic_1164 $end
$upscope $end
$scope module numeric_std $end
$upscope $end
$scope module tb_not_gate $end
$var reg 1 ! clk $end
$var reg 8 " counter[7:0] $end
$scope module dut $end
$var reg 1 # clk $end
$var reg 8 $ counter[7:0] $end
$var reg 8 % cnt[7:0] $end
$upscope $end
$upscope $end
$enddefinitions $end
#0
0!
b00000000 "
0#
b00000000 $
b00000000 %
#10000000
1!
b00000001 "
1#
b00000001 $
b00000001 %
#20000000
0!
0#
#30000000
1!
b00000010 "
1#
b00000010 $
b00000010 %
#40000000
0!
0#
#50000000
1!
b00000011 "
1#
b00000011 $
b00000011 %
#60000000
0!
0#
#70000000
1!
b00000100 "
1#
b00000100 $
b00000100 %
#80000000
0!
0#
#90000000
1!
b00000101 "
1#
b00000101 $
b00000101 %
#100000000
0!
0#
#110000000
1!
b00000110 "
1#
b00000110 $
b00000110 %
#120000000
0!
0#
#130000000
1!
b00000111 "
1#
b00000111 $
b00000111 %
#140000000
0!
0#
#150000000
1!
b00001000 "
1#
b00001000 $
b00001000 %
#160000000
0!
0#
#170000000
1!
b00001001 "
1#
b00001001 $
b00001001 %
#180000000
0!
0#
#190000000
1!
b00001010 "
1#
b00001010 $
b00001010 %
#200000000
0!
0#
#210000000
1!
b00001011 "
1#
b00001011 $
b00001011 %
#220000000
0!
0#
#230000000
1!
b00001100 "
1#
b00001100 $
b00001100 %
#240000000
0!
0#
#250000000
1!
b00001101 "
1#
b00001101 $
b00001101 %
#260000000
0!
0#
#270000000
1!
b00001110 "
1#
b00001110 $
b00001110 %
#280000000
0!
0#
#290000000
1!
b00001111 "
1#
b00001111 $
b00001111 %
#300000000
0!
0#
#310000000
1!
b00010000 "
1#
b00010000 $
b00010000 %
#320000000
0!
0#
#330000000
1!
b00010001 "
1#
b00010001 $
b00010001 %
#340000000
0!
0#
#350000000
1!
b00010010 "
1#
b00010010 $
b00010010 %
#360000000
0!
0#
#370000000
1!
b00010011 "
1#
b00010011 $
b00010011 %
#380000000
0!
0#
#390000000
1!
b00010100 "
1#
b00010100 $
b00010100 %
#400000000
0!
0#
#410000000
1!
b00010101 "
1#
b00010101 $
b00010101 %
#420000000
0!
0#
#430000000
1!
b00010110 "
1#
b00010110 $
b00010110 %
#440000000
0!
0#
#450000000
1!
b00010111 "
1#
b00010111 $
b00010111 %
#460000000
0!
0#
#470000000
1!
b00011000 "
1#
b00011000 $
b00011000 %
#480000000
0!
0#
#490000000
1!
b00011001 "
1#
b00011001 $
b00011001 %
#500000000
0!
0#
#510000000
1!
b00011010 "
1#
b00011010 $
b00011010 %
#520000000
0!
0#
#530000000
1!
b00011011 "
1#
b00011011 $
b00011011 %
#540000000
0!
0#
#550000000
1!
b00011100 "
1#
b00011100 $
b00011100 %
#560000000
0!
0#
#570000000
1!
b00011101 "
1#
b00011101 $
b00011101 %
#580000000
0!
0#
#590000000
1!
b00011110 "
1#
b00011110 $
b00011110 %
#600000000
0!
0#
#610000000
1!
b00011111 "
1#
b00011111 $
b00011111 %
