fifo/fifo.vhd
library ieee;
use ieee.std_logic_1164.all;
use ieee.numeric_std.all;

library work;
  use work.gray_pkg.all;

entity fifo is
  port (
    wclk   : in    std_logic;
    wrst_n : in    std_logic;
    wr_en  : in    std_logic;
    wfull  : out   std_logic := '0';
    wdrop  : out   std_logic;
    wvalue : in std_logic;

    

    rclk   : in    std_logic;
    rrst_n : in    std_logic;
    rd_en  : in    std_logic;
    rempty : out   std_logic := '1';
    rvalue : out   std_logic
  );

end entity fifo;

architecture rtl of fifo is
    signal data: std_logic_vector(7 downto 0) := (others => '0');

    signal wptr: unsigned(3 downto 0) := (others => '0');

    signal rptr: unsigned(3 downto 0) := (others => '0');

    -- sync for the write half
    signal gray_wptr_desync: unsigned(3 downto 0) := (others => '0');
  
    signal w_sync: unsigned(3 downto 0) := (others => '0');
    signal gray_wptr_sync: unsigned(3 downto 0) := (others => '0');
-- sync for the read half
    signal gray_rptr_desync: unsigned(3 downto 0) := (others => '0');
  
    signal r_sync: unsigned(3 downto 0) := (others => '0');
    signal gray_rptr_sync: unsigned(3 downto 0) := (others => '0');

begin

    gray_wptr_desync <= to_gray((wptr));
    gray_rptr_desync <= to_gray((rptr));

    -- Write part
    process(wclk)
      begin

        if rising_edge(wclk) then
          -- Sync wirering write
          w_sync <= gray_wptr_desync;

          -- Sync wirering read
          gray_rptr_sync <= r_sync;

          if wfull = '1' then
          if (to_gray(wptr)(3) /= gray_rptr_sync(3)) and (to_gray(wptr)(2) /= gray_rptr_sync(2)) and (to_gray(wptr)(1 downto 0) = gray_rptr_sync(1 downto 0)) then
              wfull <= '1';
            else
              wfull <= '0';
            end if;

          elsif wr_en = '1' then
            data(to_integer(wptr(2 downto 0))) <= wvalue;
            wptr <= wptr +1;

          if (to_gray(wptr + 1)(3) /= gray_rptr_sync(3)) and (to_gray(wptr + 1)(2) /= gray_rptr_sync(2)) and (to_gray(wptr + 1)(1 downto 0) = gray_rptr_sync(1 downto 0)) then
              wfull <= '1';
            else
              wfull <= '0';
            end if;

          end if;
        end if;

    end process;

    -- Read part
    process(rclk)
      begin

        if rising_edge(rclk) then
          r_sync <= gray_rptr_desync;

          gray_wptr_sync <= w_sync;

          if rempty = '1' then
            if gray_rptr_desync = gray_wptr_sync then
              rempty <= '1';
            else
              rempty <= '0';
            end if;
          elsif rd_en = '1' then 
            rvalue <= data(to_integer(rptr(2 downto 0)));
            rptr <= rptr + 1;

              if to_gray(rptr +1) = gray_wptr_sync then
                rempty <= '1';
              else
                rempty <= '0';
              end if;
          end if;
        end if;

    end process;

end architecture rtl;

fifo/tb_fifo.vhd
--=====================================================================
-- tb_fifo -- self checking testbench for the asynchronous fifo
--
-- What it does
--   * runs two independent clocks (write 100 MHz, read ~59 MHz) so the
--     gray code / synchroniser path is actually exercised
--   * pushes a known bit pattern in, pops it out again and compares
--   * checks rempty / wfull at the moments where they must change
--   * prints a PASS / FAIL summary at the end
--
-- What to look at in the wave view (all of it lives at the top level)
--   phase       which test step is running, see the PH_* constants
--   n_written   how many bits have been pushed so far
--   n_read      how many bits have been popped so far
--   n_errors    running error count, must stay 0
--   expected    what the next pop should return
--   got         what the pop actually returned
--   check_ok    pulses high on a good pop, low on a bad one
--
-- Test steps
--   1 PH_RESET   both domains in reset
--   2 PH_FLAGS   after reset: empty must be 1, full must be 0
--   3 PH_SINGLE  push 1 bit, it must show up, pop it, empty again
--   4 PH_FILL    push DEPTH bits, wfull must go high
--   5 PH_DRAIN   pop everything, rempty must go high
--   6 PH_STREAM  push and pop at the same time across both clocks
--   7 PH_DONE    summary
--=====================================================================

library ieee;
  use ieee.std_logic_1164.all;
  use ieee.numeric_std.all;

library std;
  use std.env.all;

entity tb_fifo is
end entity tb_fifo;

architecture sim of tb_fifo is

  -- ------------------------------------------------------------------
  -- knobs
  -- ------------------------------------------------------------------
  constant WCLK_PERIOD : time    := 10 ns;              -- write domain
  constant RCLK_PERIOD : time    := 17 ns;              -- read domain, on purpose not a multiple
  constant DEPTH       : natural := 8;                  -- entries fifo.vhd can hold
  constant STREAM_N    : natural := 24;                 -- bits pushed in the streaming step
  constant POP_TIMEOUT : time    := 60 * RCLK_PERIOD;   -- how long a single pop may take
  constant SIM_TIMEOUT : time    := 100 us;             -- hard stop, keeps a broken dut from hanging

  -- test data, bit i of the stream is stream_bit(i)
  constant PATTERN : std_logic_vector(0 to 15) := "1011000111010010";

  function stream_bit (i : natural) return std_logic is
  begin
    return PATTERN(i mod PATTERN'length);
  end function stream_bit;

  -- ------------------------------------------------------------------
  -- phase codes, shown as a number in the wave view
  -- ------------------------------------------------------------------
  constant PH_RESET  : unsigned(3 downto 0) := x"1";
  constant PH_FLAGS  : unsigned(3 downto 0) := x"2";
  constant PH_SINGLE : unsigned(3 downto 0) := x"3";
  constant PH_FILL   : unsigned(3 downto 0) := x"4";
  constant PH_DRAIN  : unsigned(3 downto 0) := x"5";
  constant PH_STREAM : unsigned(3 downto 0) := x"6";
  constant PH_DONE   : unsigned(3 downto 0) := x"7";

  -- ------------------------------------------------------------------
  -- dut connections
  -- ------------------------------------------------------------------
  signal wclk   : std_logic := '0';
  signal wrst_n : std_logic := '0';
  signal wr_en  : std_logic := '0';
  signal wvalue : std_logic := '0';
  signal wfull  : std_logic;
  signal wdrop  : std_logic;

  signal rclk   : std_logic := '0';
  signal rrst_n : std_logic := '0';
  signal rd_en  : std_logic := '0';
  signal rempty : std_logic;
  signal rvalue : std_logic;

  -- ------------------------------------------------------------------
  -- observation / scoreboard, this is the stuff you want on screen
  -- ------------------------------------------------------------------
  signal phase     : unsigned(3 downto 0) := (others => '0');
  signal n_written : unsigned(7 downto 0) := (others => '0');
  signal n_read    : unsigned(7 downto 0) := (others => '0');
  signal n_errors  : unsigned(7 downto 0) := (others => '0');

  signal expected  : std_logic := 'U';
  signal got       : std_logic := 'U';
  signal check_ok  : std_logic := 'U';

  -- two error counters so that no signal has two drivers, summed below
  signal err_main  : unsigned(7 downto 0) := (others => '0');
  signal err_check : unsigned(7 downto 0) := (others => '0');

  -- handshake between the two halves of the testbench
  signal rd_active : std_logic := '0';   -- 1 = reader is allowed to pop
  signal clocks_on : boolean   := true;

begin

  -- ==================================================================
  -- clocks, two unrelated frequencies
  -- ==================================================================
  wclk <= not wclk after WCLK_PERIOD / 2 when clocks_on else '0';
  rclk <= not rclk after RCLK_PERIOD / 2 when clocks_on else '0';

  n_errors <= err_main + err_check;

  -- ==================================================================
  -- device under test
  -- ==================================================================
  dut : entity work.fifo
    port map (
      wclk   => wclk,
      wrst_n => wrst_n,
      wr_en  => wr_en,
      wfull  => wfull,
      wdrop  => wdrop,
      wvalue => wvalue,

      rclk   => rclk,
      rrst_n => rrst_n,
      rd_en  => rd_en,
      rempty => rempty,
      rvalue => rvalue
    );

  -- ==================================================================
  -- write side, this process owns the test flow
  -- ==================================================================
  stimulus : process

    -- push one bit, index decides the value so the reader knows it too.
    -- wr_en is held until the dut actually takes the write: reading wfull
    -- right after the wait gives the value the dut sampled at that edge, so
    -- wfull = '0' there means this write landed. without this the fifo can
    -- fill up between the check and the edge and the bit is lost silently.
    procedure push (i : natural) is
    begin
      wait until rising_edge(wclk);
      wvalue <= stream_bit(i);
      wr_en  <= '1';
      loop
        wait until rising_edge(wclk);
        exit when wfull = '0';
      end loop;
      wr_en  <= '0';
      n_written <= n_written + 1;
    end procedure push;

    procedure check (cond : boolean; msg : string) is
    begin
      if not cond then
        err_main <= err_main + 1;
        report "CHECK FAILED at " & time'image(now) & ": " & msg severity error;
      end if;
    end procedure check;

  begin

    ---------------------------------------------------------------- 1
    phase <= PH_RESET;
    report "phase 1: reset";
    wrst_n <= '0';
    rrst_n <= '0';
    wait for 5 * WCLK_PERIOD;
    wrst_n <= '1';
    rrst_n <= '1';
    wait for 5 * WCLK_PERIOD;

    ---------------------------------------------------------------- 2
    phase <= PH_FLAGS;
    report "phase 2: flags after reset";
    check(rempty = '1', "rempty should be 1 after reset, is " & std_logic'image(rempty));
    check(wfull  = '0', "wfull should be 0 after reset, is "  & std_logic'image(wfull));

    ---------------------------------------------------------------- 3
    phase <= PH_SINGLE;
    report "phase 3: single bit in, single bit out";
    push(0);
    wait for 4 * RCLK_PERIOD;                       -- let the pointer cross over
    check(rempty = '0', "rempty should drop after one write");

    rd_active <= '1';                               -- let the reader take it
    wait until n_read = 1 for POP_TIMEOUT;
    check(n_read = 1, "reader did not pop the first bit in time");
    rd_active <= '0';

    wait for 4 * RCLK_PERIOD;
    check(rempty = '1', "rempty should be 1 again after the fifo was drained");

    ---------------------------------------------------------------- 4
    phase <= PH_FILL;
    report "phase 4: fill it up, wfull must rise";
    for i in 1 to DEPTH loop
      push(i);
    end loop;
    wait for 2 * WCLK_PERIOD;
    check(wfull = '1', "wfull should be 1 after DEPTH writes");

    -- a write while full must not be swallowed silently
    wait until rising_edge(wclk);
    wvalue <= '1';
    wr_en  <= '1';
    wait until rising_edge(wclk);
    wr_en  <= '0';
    check(wfull = '1', "wfull must stay 1 while the fifo is full");

    ---------------------------------------------------------------- 5
    phase <= PH_DRAIN;
    report "phase 5: drain it, rempty must rise";
    rd_active <= '1';
    wait until n_read = DEPTH + 1 for DEPTH * POP_TIMEOUT;
    check(n_read = DEPTH + 1, "reader did not drain the fifo in time");
    rd_active <= '0';

    wait for 4 * RCLK_PERIOD;
    check(rempty = '1', "rempty should be 1 after the drain");
    check(wfull  = '0', "wfull should be 0 after the drain");

    ---------------------------------------------------------------- 6
    phase <= PH_STREAM;
    report "phase 6: writing and reading at the same time";
    rd_active <= '1';
    for i in DEPTH + 1 to DEPTH + STREAM_N loop
      push(i);   -- push blocks by itself while the fifo is full
    end loop;

    wait until n_read = n_written for STREAM_N * POP_TIMEOUT;
    check(n_read = n_written,
          "reader lost data: wrote " & integer'image(to_integer(n_written)) &
          ", read " & integer'image(to_integer(n_read)));
    rd_active <= '0';

    ---------------------------------------------------------------- 7
    phase <= PH_DONE;
    wait for 10 * RCLK_PERIOD;

    report "----------------------------------------------------";
    report "bits written : " & integer'image(to_integer(n_written));
    report "bits read    : " & integer'image(to_integer(n_read));
    report "errors       : " & integer'image(to_integer(n_errors));
    if n_errors = 0 then
      report "RESULT: PASS" severity note;
    else
      report "RESULT: FAIL" severity error;
    end if;
    report "----------------------------------------------------";

    clocks_on <= false;
    wait for 1 ns;
    finish;

  end process stimulus;

  -- ==================================================================
  -- read side, pops whenever it is allowed to and scores every bit
  -- ==================================================================
  checker : process
    variable idx : natural := 0;   -- how many bits we have popped
  begin

    wait until rrst_n = '1';

    loop
      wait until rising_edge(rclk);

      if rd_active = '1' and rempty = '0' then

        expected <= stream_bit(idx);

        rd_en <= '1';
        wait until rising_edge(rclk);     -- dut samples rd_en here
        rd_en <= '0';
        wait until rising_edge(rclk);     -- rvalue is registered by now

        got <= rvalue;

        if rvalue = stream_bit(idx) then
          check_ok <= '1';
        else
          check_ok <= '0';
          err_check <= err_check + 1;
          report "DATA MISMATCH at " & time'image(now) &
                 ": bit " & integer'image(idx) &
                 " expected " & std_logic'image(stream_bit(idx)) &
                 " got " & std_logic'image(rvalue) severity error;
        end if;

        idx    := idx + 1;
        n_read <= to_unsigned(idx, n_read'length);
      end if;

    end loop;

  end process checker;

  -- ==================================================================
  -- watchdog, so a stuck dut still ends the simulation
  -- ==================================================================
  watchdog : process
  begin
    wait for SIM_TIMEOUT;
    report "WATCHDOG: simulation did not finish within " & time'image(SIM_TIMEOUT) &
           " -- the dut is most likely stuck" severity failure;
    wait;
  end process watchdog;

end architecture sim;

fifo/tb_fifo.vcd
$date
  Thu Aug 27 15:03:48 2026
$end
$version
  GHDL v0
$end
$timescale
  1 fs
$end
$scope module standard $end
$upscope $end
$scope module textio $end
$upscope $end
$scope module std_logic_1164 $end
$upscope $end
$scope module numeric_std $end
$upscope $end
$scope module env $end
$upscope $end
$scope module gray_pkg $end
$upscope $end
$scope module tb_fifo $end
$var reg 1 ! wclk $end
$var reg 1 " wrst_n $end
$var reg 1 # wr_en $end
$var reg 1 $ wvalue $end
$var reg 1 % wfull $end
$var reg 1 & wdrop $end
$var reg 1 ' rclk $end
$var reg 1 ( rrst_n $end
$var reg 1 ) rd_en $end
$var reg 1 * rempty $end
$var reg 1 + rvalue $end
$var reg 4 , phase[3:0] $end
$var reg 8 - n_written[7:0] $end
$var reg 8 . n_read[7:0] $end
$var reg 8 / n_errors[7:0] $end
$var reg 1 0 expected $end
$var reg 1 1 got $end
$var reg 1 2 check_ok $end
$var reg 8 3 err_main[7:0] $end
$var reg 8 4 err_check[7:0] $end
$var reg 1 5 rd_active $end
$var reg 1 6 clocks_on $end
$scope module dut $end
$var reg 1 7 wclk $end
$var reg 1 8 wrst_n $end
$var reg 1 9 wr_en $end
$var reg 1 : wfull $end
$var reg 1 ; wdrop $end
$var reg 1 < wvalue $end
$var reg 1 = rclk $end
$var reg 1 > rrst_n $end
$var reg 1 ? rd_en $end
$var reg 1 @ rempty $end
$var reg 1 A rvalue $end
$var reg 8 B data[7:0] $end
$var reg 4 C wptr[3:0] $end
$var reg 4 D rptr[3:0] $end
$var reg 4 E gray_wptr_desync[3:0] $end
$var reg 4 F w_sync[3:0] $end
$var reg 4 G gray_wptr_sync[3:0] $end
$var reg 4 H gray_rptr_desync[3:0] $end
$var reg 4 I r_sync[3:0] $end
$var reg 4 J gray_rptr_sync[3:0] $end
$upscope $end
$upscope $end
$enddefinitions $end
#0
0!
0"
0#
0$
0%
U&
0'
0(
0)
1*
U+
b0001 ,
b00000000 -
b00000000 .
b00000000 /
U0
U1
U2
b00000000 3
b00000000 4
05
16
07
08
09
0:
U;
0<
0=
0>
0?
1@
UA
b00000000 B
b0000 C
b0000 D
b0000 E
b0000 F
b0000 G
b0000 H
b0000 I
b0000 J
#5000000
1!
17
#8500000
1'
1=
#10000000
0!
07
#15000000
1!
17
#17000000
0'
0=
#20000000
0!
07
#25000000
1!
17
#25500000
1'
1=
#30000000
0!
07
#34000000
0'
0=
#35000000
1!
17
#40000000
0!
07
#42500000
1'
1=
#45000000
1!
17
#50000000
0!
1"
1(
07
18
1>
#51000000
0'
0=
#55000000
1!
17
#59500000
1'
1=
#60000000
0!
07
#65000000
1!
17
#68000000
0'
0=
#70000000
0!
07
#75000000
1!
17
#76500000
1'
1=
#80000000
0!
07
#85000000
1!
0'
17
0=
#90000000
0!
07
#93500000
1'
1=
#95000000
1!
17
#100000000
0!
b0011 ,
07
#102000000
0'
0=
#105000000
1!
1#
1$
17
19
1<
#110000000
0!
07
#110500000
1'
1=
#115000000
1!
0#
b00000001 -
17
09
b00000001 B
b0001 C
b0001 E
#119000000
0'
0=
#120000000
0!
07
#125000000
1!
17
b0001 F
#127500000
1'
1=
b0001 G
#130000000
0!
07
#135000000
1!
17
#136000000
0'
0=
#140000000
0!
07
#144500000
1'
0*
1=
0@
#145000000
1!
17
#150000000
0!
07
#153000000
0'
0=
#155000000
1!
17
#160000000
0!
07
#161500000
1'
1=
#165000000
1!
17
#170000000
0!
0'
07
0=
#175000000
1!
17
#178500000
1'
1=
#180000000
0!
07
#183000000
15
#185000000
1!
17
#187000000
0'
0=
#190000000
0!
07
#195000000
1!
17
#195500000
1'
1)
10
1=
1?
#200000000
0!
07
#204000000
0'
0=
#205000000
1!
17
#210000000
0!
07
#212500000
1'
0)
1*
1+
1=
0?
1@
1A
b0001 D
b0001 H
#215000000
1!
17
#220000000
0!
07
#221000000
0'
0=
#225000000
1!
17
#229500000
1'
b00000001 .
11
12
05
1=
b0001 I
#230000000
0!
07
#235000000
1!
17
b0001 J
#238000000
0'
0=
#240000000
0!
07
#245000000
1!
17
#246500000
1'
1=
#250000000
0!
07
#255000000
1!
0'
17
0=
#260000000
0!
07
#263500000
1'
1=
#265000000
1!
17
#270000000
0!
07
#272000000
0'
0=
#275000000
1!
17
#280000000
0!
07
#280500000
1'
1=
#285000000
1!
17
#289000000
0'
0=
#290000000
0!
07
#295000000
1!
17
#297500000
1'
b0100 ,
1=
#300000000
0!
07
#305000000
1!
1#
0$
17
19
0<
#306000000
0'
0=
#310000000
0!
07
#314500000
1'
1=
#315000000
1!
0#
b00000010 -
17
09
b0010 C
b0011 E
#320000000
0!
07
#323000000
0'
0=
#325000000
1!
1#
1$
17
19
1<
b0011 F
#330000000
0!
07
#331500000
1'
1=
b0011 G
#335000000
1!
0#
b00000011 -
17
09
b00000101 B
b0011 C
b0010 E
#340000000
0!
0'
07
0=
#345000000
1!
1#
17
19
b0010 F
#348500000
1'
0*
1=
0@
b0010 G
#350000000
0!
07
#355000000
1!
0#
b00000100 -
17
09
b00001101 B
b0100 C
b0110 E
#357000000
0'
0=
#360000000
0!
07
#365000000
1!
1#
0$
17
19
0<
b0110 F
#365500000
1'
1=
b0110 G
#370000000
0!
07
#374000000
0'
0=
#375000000
1!
0#
b00000101 -
17
09
b0101 C
b0111 E
#380000000
0!
07
#382500000
1'
1=
#385000000
1!
1#
17
19
b0111 F
#390000000
0!
07
#391000000
0'
0=
#395000000
1!
0#
b00000110 -
17
09
b0110 C
b0101 E
#399500000
1'
1=
b0111 G
#400000000
0!
07
#405000000
1!
1#
17
19
b0101 F
#408000000
0'
0=
#410000000
0!
07
#415000000
1!
0#
b00000111 -
17
09
b0111 C
b0100 E
#416500000
1'
1=
b0101 G
#420000000
0!
07
#425000000
1!
1#
1$
0'
17
19
1<
0=
b0100 F
#430000000
0!
07
#433500000
1'
1=
b0100 G
#435000000
1!
0#
b00001000 -
17
09
b10001101 B
b1000 C
b1100 E
#440000000
0!
07
#442000000
0'
0=
#445000000
1!
1#
17
19
b1100 F
#450000000
0!
07
#450500000
1'
1=
b1100 G
#455000000
1!
0#
1%
b00001001 -
17
09
1:
b1001 C
b1101 E
#459000000
0'
0=
#460000000
0!
07
#465000000
1!
17
b1101 F
#467500000
1'
1=
b1101 G
#470000000
0!
07
#475000000
1!
17
#476000000
0'
0=
#480000000
0!
07
#484500000
1'
1=
#485000000
1!
1#
17
19
#490000000
0!
07
#493000000
0'
0=
#495000000
1!
0#
b0101 ,
15
17
09
#500000000
0!
07
#501500000
1'
1)
00
1=
1?
#505000000
1!
17
#510000000
0!
0'
07
0=
#515000000
1!
17
#518500000
1'
0)
0+
1=
0?
0A
b0010 D
b0011 H
#520000000
0!
07
#525000000
1!
17
#527000000
0'
0=
#530000000
0!
07
#535000000
1!
17
#535500000
1'
b00000010 .
01
1=
b0011 I
#540000000
0!
07
#544000000
0'
0=
#545000000
1!
17
b0011 J
#550000000
0!
07
#552500000
1'
1)
10
1=
1?
#555000000
1!
0%
17
0:
#560000000
0!
07
#561000000
0'
0=
#565000000
1!
17
#569500000
1'
0)
1+
1=
0?
1A
b0011 D
b0010 H
#570000000
0!
07
#575000000
1!
17
#578000000
0'
0=
#580000000
0!
07
#585000000
1!
17
#586500000
1'
b00000011 .
11
1=
b0010 I
#590000000
0!
07
#595000000
1!
0'
17
0=
b0010 J
#600000000
0!
07
#603500000
1'
1)
1=
1?
#605000000
1!
17
#610000000
0!
07
#612000000
0'
0=
#615000000
1!
17
#620000000
0!
07
#620500000
1'
0)
1=
0?
b0100 D
b0110 H
#625000000
1!
17
#629000000
0'
0=
#630000000
0!
07
#635000000
1!
17
#637500000
1'
b00000100 .
1=
b0110 I
#640000000
0!
07
#645000000
1!
17
b0110 J
#646000000
0'
0=
#650000000
0!
07
#654500000
1'
1)
00
1=
1?
#655000000
1!
17
#660000000
0!
07
#663000000
0'
0=
#665000000
1!
17
#670000000
0!
07
#671500000
1'
0)
0+
1=
0?
0A
b0101 D
b0111 H
#675000000
1!
17
#680000000
0!
0'
07
0=
#685000000
1!
17
#688500000
1'
b00000101 .
01
1=
b0111 I
#690000000
0!
07
#695000000
1!
17
b0111 J
#697000000
0'
0=
#700000000
0!
07
#705000000
1!
17
#705500000
1'
1)
1=
1?
#710000000
0!
07
#714000000
0'
0=
#715000000
1!
17
#720000000
0!
07
#722500000
1'
0)
1=
0?
b0110 D
b0101 H
#725000000
1!
17
#730000000
0!
07
#731000000
0'
0=
#735000000
1!
17
#739500000
1'
b00000110 .
1=
b0101 I
#740000000
0!
07
#745000000
1!
17
b0101 J
#748000000
0'
0=
#750000000
0!
07
#755000000
1!
17
#756500000
1'
1)
1=
1?
#760000000
0!
07
#765000000
1!
0'
17
0=
#770000000
0!
07
#773500000
1'
0)
1=
0?
b0111 D
b0100 H
#775000000
1!
17
#780000000
0!
07
#782000000
0'
0=
#785000000
1!
17
#790000000
0!
07
#790500000
1'
b00000111 .
1=
b0100 I
#795000000
1!
17
b0100 J
#799000000
0'
0=
#800000000
0!
07
#805000000
1!
17
#807500000
1'
1)
10
1=
1?
#810000000
0!
07
#815000000
1!
17
#816000000
0'
0=
#820000000
0!
07
#824500000
1'
0)
1+
1=
0?
1A
b1000 D
b1100 H
#825000000
1!
17
#830000000
0!
07
#833000000
0'
0=
#835000000
1!
17
#840000000
0!
07
#841500000
1'
b00001000 .
11
1=
b1100 I
#845000000
1!
17
b1100 J
#850000000
0!
0'
07
0=
#855000000
1!
17
#858500000
1'
1)
1=
1?
#860000000
0!
07
#865000000
1!
17
#867000000
0'
0=
#870000000
0!
07
#875000000
1!
17
#875500000
1'
0)
1*
1=
0?
1@
b1001 D
b1101 H
#880000000
0!
07
#884000000
0'
0=
#885000000
1!
17
#890000000
0!
07
#892500000
1'
b00001001 .
05
1=
b1101 I
#895000000
1!
17
b1101 J
#900000000
0!
07
#901000000
0'
0=
#905000000
1!
17
#909500000
1'
1=
#910000000
0!
07
#915000000
1!
17
#918000000
0'
0=
#920000000
0!
07
#925000000
1!
17
#926500000
1'
1=
#930000000
0!
07
#935000000
1!
0'
17
0=
#940000000
0!
07
#943500000
1'
1=
#945000000
1!
17
#950000000
0!
07
#952000000
0'
0=
#955000000
1!
17
#960000000
0!
07
#960500000
1'
b0110 ,
15
1=
#965000000
1!
1#
17
19
#969000000
0'
0=
#970000000
0!
07
#975000000
1!
0#
b00001010 -
17
09
b10001111 B
b1010 C
b1111 E
#977500000
1'
1=
#980000000
0!
07
#985000000
1!
1#
0$
17
19
0<
b1111 F
#986000000
0'
0=
#990000000
0!
07
#994500000
1'
1=
b1111 G
#995000000
1!
0#
b00001011 -
17
09
b10001011 B
b1011 C
b1110 E
#1000000000
0!
07
#1003000000
0'
0=
#1005000000
1!
1#
1$
17
19
1<
b1110 F
#1010000000
0!
07
#1011500000
1'
0*
1=
0@
b1110 G
#1015000000
1!
0#
b00001100 -
17
09
b1100 C
b1010 E
#1020000000
0!
0'
07
0=
#1025000000
1!
1#
0$
17
19
0<
b1010 F
#1028500000
1'
1)
1=
1?
b1010 G
#1030000000
0!
07
#1035000000
1!
0#
b00001101 -
17
09
b1101 C
b1011 E
#1037000000
0'
0=
#1040000000
0!
07
#1045000000
1!
1#
17
19
b1011 F
#1045500000
1'
0)
1=
0?
b1010 D
b1011 G
b1111 H
#1050000000
0!
07
#1054000000
0'
0=
#1055000000
1!
0#
b00001110 -
17
09
b1110 C
b1001 E
#1060000000
0!
07
#1062500000
1'
b00001010 .
1=
b1111 I
#1065000000
1!
1#
1$
17
19
1<
b1001 F
b1111 J
#1070000000
0!
07
#1071000000
0'
0=
#1075000000
1!
0#
b00001111 -
17
09
b11001011 B
b1111 C
b1000 E
#1079500000
1'
1)
00
1=
1?
b1001 G
#1080000000
0!
07
#1085000000
1!
1#
0$
17
19
0<
b1000 F
#1088000000
0'
0=
#1090000000
0!
07
#1095000000
1!
0#
b00010000 -
17
09
b01001011 B
b0000 C
b0000 E
#1096500000
1'
0)
0+
1=
0?
0A
b1011 D
b1000 G
b1110 H
#1100000000
0!
07
#1105000000
1!
1#
1$
0'
17
19
1<
0=
b0000 F
#1110000000
0!
07
#1113500000
1'
b00001011 .
01
1=
b0000 G
b1110 I
#1115000000
1!
0#
b00010001 -
17
09
b0001 C
b0001 E
b1110 J
#1120000000
0!
07
#1122000000
0'
0=
#1125000000
1!
1#
0$
17
19
0<
b0001 F
#1130000000
0!
07
#1130500000
1'
1)
10
1=
1?
b0001 G
#1135000000
1!
0#
b00010010 -
17
09
b01001001 B
b0010 C
b0011 E
#1139000000
0'
0=
#1140000000
0!
07
#1145000000
1!
1#
1$
17
19
1<
b0011 F
#1147500000
1'
0)
1+
1=
0?
1A
b1100 D
b0011 G
b1010 H
#1150000000
0!
07
#1155000000
1!
0#
1%
b00010011 -
17
09
1:
b01001101 B
b0011 C
b0010 E
#1156000000
0'
0=
#1160000000
0!
07
#1164500000
1'
b00001100 .
11
1=
b1010 I
#1165000000
1!
1#
17
19
b0010 F
b1010 J
#1170000000
0!
07
#1173000000
0'
0=
#1175000000
1!
0%
17
0:
#1180000000
0!
07
#1181500000
1'
1)
00
1=
1?
b0010 G
#1185000000
1!
0#
1%
b00010100 -
17
09
1:
b0100 C
b0110 E
#1190000000
0!
0'
07
0=
#1195000000
1!
1#
0$
17
19
0<
b0110 F
#1198500000
1'
0)
0+
1=
0?
0A
b1101 D
b0110 G
b1011 H
#1200000000
0!
07
#1205000000
1!
17
#1207000000
0'
0=
#1210000000
0!
07
#1215000000
1!
17
#1215500000
1'
b00001101 .
01
1=
b1011 I
#1220000000
0!
07
#1224000000
0'
0=
#1225000000
1!
17
b1011 J
#1230000000
0!
07
#1232500000
1'
1)
1=
1?
#1235000000
1!
0%
17
0:
#1240000000
0!
07
#1241000000
0'
0=
#1245000000
1!
0#
1%
b00010101 -
17
09
1:
b0101 C
b0111 E
#1249500000
1'
0)
1=
0?
b1110 D
b1001 H
#1250000000
0!
07
#1255000000
1!
1#
17
19
b0111 F
#1258000000
0'
0=
#1260000000
0!
07
#1265000000
1!
17
#1266500000
1'
b00001110 .
1=
b0111 G
b1001 I
#1270000000
0!
07
#1275000000
1!
0'
17
0=
b1001 J
#1280000000
0!
07
#1283500000
1'
1)
10
1=
1?
#1285000000
1!
0%
17
0:
#1290000000
0!
07
#1292000000
0'
0=
#1295000000
1!
0#
1%
b00010110 -
17
09
1:
b0110 C
b0101 E
#1300000000
0!
07
#1300500000
1'
0)
1+
1=
0?
1A
b1111 D
b1000 H
#1305000000
1!
1#
17
19
b0101 F
#1309000000
0'
0=
#1310000000
0!
07
#1315000000
1!
17
#1317500000
1'
b00001111 .
11
1=
b0101 G
b1000 I
#1320000000
0!
07
#1325000000
1!
17
b1000 J
#1326000000
0'
0=
#1330000000
0!
07
#1334500000
1'
1)
00
1=
1?
#1335000000
1!
0%
17
0:
#1340000000
0!
07
#1343000000
0'
0=
#1345000000
1!
0#
1%
b00010111 -
17
09
1:
b00001101 B
b0111 C
b0100 E
#1350000000
0!
07
#1351500000
1'
0)
0+
1=
0?
0A
b0000 D
b0000 H
#1355000000
1!
1#
1$
17
19
1<
b0100 F
#1360000000
0!
0'
07
0=
#1365000000
1!
17
#1368500000
1'
b00010000 .
01
1=
b0100 G
b0000 I
#1370000000
0!
07
#1375000000
1!
17
b0000 J
#1377000000
0'
0=
#1380000000
0!
07
#1385000000
1!
0%
17
0:
#1385500000
1'
1)
10
1=
1?
#1390000000
0!
07
#1394000000
0'
0=
#1395000000
1!
0#
1%
b00011000 -
17
09
1:
b10001101 B
b1000 C
b1100 E
#1400000000
0!
07
#1402500000
1'
0)
1+
1=
0?
1A
b0001 D
b0001 H
#1405000000
1!
1#
17
19
b1100 F
#1410000000
0!
07
#1411000000
0'
0=
#1415000000
1!
17
#1419500000
1'
b00010001 .
11
1=
b1100 G
b0001 I
#1420000000
0!
07
#1425000000
1!
17
b0001 J
#1428000000
0'
0=
#1430000000
0!
07
#1435000000
1!
0%
17
0:
#1436500000
1'
1)
00
1=
1?
#1440000000
0!
07
#1445000000
1!
0#
1%
0'
b00011001 -
17
09
1:
0=
b1001 C
b1101 E
#1450000000
0!
07
#1453500000
1'
0)
0+
1=
0?
0A
b0010 D
b0011 H
#1455000000
1!
1#
17
19
b1101 F
#1460000000
0!
07
#1462000000
0'
0=
#1465000000
1!
17
#1470000000
0!
07
#1470500000
1'
b00010010 .
01
1=
b1101 G
b0011 I
#1475000000
1!
17
b0011 J
#1479000000
0'
0=
#1480000000
0!
07
#1485000000
1!
0%
17
0:
#1487500000
1'
1)
10
1=
1?
#1490000000
0!
07
#1495000000
1!
0#
1%
b00011010 -
17
09
1:
b10001111 B
b1010 C
b1111 E
#1496000000
0'
0=
#1500000000
0!
07
#1504500000
1'
0)
1+
1=
0?
1A
b0011 D
b0010 H
#1505000000
1!
1#
0$
17
19
0<
b1111 F
#1510000000
0!
07
#1513000000
0'
0=
#1515000000
1!
17
#1520000000
0!
07
#1521500000
1'
b00010011 .
11
1=
b1111 G
b0010 I
#1525000000
1!
17
b0010 J
#1530000000
0!
0'
07
0=
#1535000000
1!
0%
17
0:
#1538500000
1'
1)
1=
1?
#1540000000
0!
07
#1545000000
1!
0#
1%
b00011011 -
17
09
1:
b10001011 B
b1011 C
b1110 E
#1547000000
0'
0=
#1550000000
0!
07
#1555000000
1!
1#
1$
17
19
1<
b1110 F
#1555500000
1'
0)
1=
0?
b0100 D
b1110 G
b0110 H
#1560000000
0!
07
#1564000000
0'
0=
#1565000000
1!
17
#1570000000
0!
07
#1572500000
1'
b00010100 .
1=
b0110 I
#1575000000
1!
17
b0110 J
#1580000000
0!
07
#1581000000
0'
0=
#1585000000
1!
0%
17
0:
#1589500000
1'
1)
00
1=
1?
#1590000000
0!
07
#1595000000
1!
0#
1%
b00011100 -
17
09
1:
b1100 C
b1010 E
#1598000000
0'
0=
#1600000000
0!
07
#1605000000
1!
1#
0$
17
19
0<
b1010 F
#1606500000
1'
0)
0+
1=
0?
0A
b0101 D
b1010 G
b0111 H
#1610000000
0!
07
#1615000000
1!
0'
17
0=
#1620000000
0!
07
#1623500000
1'
b00010101 .
01
1=
b0111 I
