edge_detection/edge_detection.vhd
library ieee;
use ieee.std_logic_1164.all;
use ieee.numeric_std.all;

entity edge_detection is
  port (
    clk: in std_logic;
    input: in std_logic := '0';
    safe: buffer std_logic := '0';
    bang: out std_logic := '0';
    hehe: out std_logic := '0'
  );
end entity edge_detection;

architecture rtl of edge_detection is

begin

  process (clk)
    begin
      if rising_edge(clk) then 
        safe <= input;
        bang <= not safe and input;
      end if;
      
  end process;
  
  hehe <= input xor clk;

end architecture rtl;

edge_detection/tb_edge_detection.vhd
library ieee;
use ieee.std_logic_1164.all;
use ieee.numeric_std.all;

entity tb_edge_detection is
end entity tb_edge_detection;

architecture sim of tb_edge_detection is
  signal clk:  std_logic := '0';
  signal input:  std_logic := '0';
  signal bang: std_logic := '0';

begin

  dut : entity work.edge_detection
    port map (
      clk => clk,
      input => input,
      bang => bang
    );

  stimulus : process
  begin

    wait for 10 ns;

    for i in 0 to 3 loop
      -- button is pressed 
      input <= '1';
      wait for 10 ns;
      clk <= '1';
      wait for 10 ns;
      -- now we should se bang be active 
      clk <= '0';
      wait for 10 ns;
      clk <= '1';
      wait for 10 ns;
      -- now we should se bang be inactive 
      clk <= '0';
      wait for 10 ns;
      clk <= '1';
      wait for 10 ns;
      -- now we should se bang be inactive 
      clk <= '0';
      wait for 10 ns;
      clk <= '1';
      wait for 10 ns;
      -- now we should se bang be inactive 
      clk <= '0';
      wait for 10 ns;

      input <= '0';
      wait for 10 ns;
      clk <= '1';
      wait for 10 ns;
      clk <= '0';
      wait for 10 ns;

    end loop;

    wait;

  end process;

end architecture sim;

edge_detection/tb_edge_detection.vcd
$date
  Mon Aug 24 15:57:49 2026
$end
$version
  GHDL v0
$end
$timescale
  1 fs
$end
$scope module standard $end
$upscope $end
$scope module textio $end
$upscope $end
$scope module std_logic_1164 $end
$upscope $end
$scope module numeric_std $end
$upscope $end
$scope module tb_edge_detection $end
$var reg 1 ! clk $end
$var reg 1 " input $end
$var reg 1 # bang $end
$scope module dut $end
$var reg 1 $ clk $end
$var reg 1 % input $end
$var reg 1 & safe $end
$var reg 1 ' bang $end
$var reg 1 ( hehe $end
$upscope $end
$upscope $end
$enddefinitions $end
#0
0!
0"
0#
0$
0%
0&
0'
0(
#10000000
1"
1%
1(
#20000000
1!
1#
1$
1&
1'
0(
#30000000
0!
0$
1(
#40000000
1!
0#
1$
0'
0(
#50000000
0!
0$
1(
#60000000
1!
1$
0(
#70000000
0!
0$
1(
#80000000
1!
1$
0(
#90000000
0!
0$
1(
#100000000
0"
0%
0(
#110000000
1!
1$
0&
1(
#120000000
0!
0$
0(
#130000000
1"
1%
1(
#140000000
1!
1#
1$
1&
1'
0(
#150000000
0!
0$
1(
#160000000
1!
0#
1$
0'
0(
#170000000
0!
0$
1(
#180000000
1!
1$
0(
#190000000
0!
0$
1(
#200000000
1!
1$
0(
#210000000
0!
0$
1(
#220000000
0"
0%
0(
#230000000
1!
1$
0&
1(
#240000000
0!
0$
0(
#250000000
1"
1%
1(
#260000000
1!
1#
1$
1&
1'
0(
#270000000
0!
0$
1(
#280000000
1!
0#
1$
0'
0(
#290000000
0!
0$
1(
#300000000
1!
1$
0(
#310000000
0!
0$
1(
#320000000
1!
1$
0(
#330000000
0!
0$
1(
#340000000
0"
0%
0(
#350000000
1!
1$
0&
1(
#360000000
0!
0$
0(
#370000000
1"
1%
1(
#380000000
1!
1#
1$
1&
1'
0(
#390000000
0!
0$
1(
#400000000
1!
0#
1$
0'
0(
#410000000
0!
0$
1(
#420000000
1!
1$
0(
#430000000
0!
0$
1(
#440000000
1!
1$
0(
#450000000
0!
0$
1(
#460000000
0"
0%
0(
#470000000
1!
1$
0&
1(
#480000000
0!
0$
0(
