counter/counter.vhd
library ieee;
use ieee.std_logic_1164.all;
use ieee.numeric_std.all;

entity counter is
  port (
    clk : in  std_logic;
    reset : in std_logic;
    enable : in std_logic;
    number: out std_logic_vector(7 downto 0)
  );
end entity counter;

architecture rtl of counter is
  signal num: unsigned(7 downto 0) := (others => '0');

begin
  process (clk)
    begin
      if rising_edge(clk) then
        if reset = '1' then
          num <= (others => '0');
        elsif enable = '1' then
          num <= num + 1;
        end if;
      end if;

  end process;

  number <= std_logic_vector(num);

end architecture rtl;

counter/tb_counter.vhd
library ieee;
use ieee.std_logic_1164.all;
use ieee.numeric_std.all;

entity tb_counter is
end entity tb_counter;

architecture sim of tb_counter is

  signal clk: std_logic := '0';
  signal reset: std_logic := '0';
  signal enable: std_logic := '0';
  signal counter : std_logic_vector(7 downto 0);

begin

  dut : entity work.counter
    port map (
      clk => clk,
      number => counter,
      reset => reset,
      enable => enable
    );

  stimulus : process
  begin
    enable <= '1';
    wait for 10 ns;

    for i in 0 to 30 loop
      clk <= '1';
      wait for 10 ns;
      clk <= '0';
      wait for 10 ns;
    end loop;

    reset <= '1';
    clk <= '1';
    wait for 10 ns;
    clk <= '0';
    wait for 10 ns;
    reset <= '0';

    for i in 0 to 30 loop
      clk <= '1';
      wait for 10 ns;
      clk <= '0';
      wait for 10 ns;
    end loop;

    wait;

  end process;


end architecture sim;

counter/tb_counter.vcd
$date
  Mon Aug 24 14:23:43 2026
$end
$version
  GHDL v0
$end
$timescale
  1 fs
$end
$scope module standard $end
$upscope $end
$scope module textio $end
$upscope $end
$scope module std_logic_1164 $end
$upscope $end
$scope module numeric_std $end
$upscope $end
$scope module tb_counter $end
$var reg 1 ! clk $end
$var reg 1 " reset $end
$var reg 1 # enable $end
$var reg 8 $ counter[7:0] $end
$scope module dut $end
$var reg 1 % clk $end
$var reg 1 & reset $end
$var reg 1 ' enable $end
$var reg 8 ( number[7:0] $end
$var reg 8 ) num[7:0] $end
$upscope $end
$upscope $end
$enddefinitions $end
#0
0!
0"
1#
b00000000 $
0%
0&
1'
b00000000 (
b00000000 )
#10000000
1!
b00000001 $
1%
b00000001 (
b00000001 )
#20000000
0!
0%
#30000000
1!
b00000010 $
1%
b00000010 (
b00000010 )
#40000000
0!
0%
#50000000
1!
b00000011 $
1%
b00000011 (
b00000011 )
#60000000
0!
0%
#70000000
1!
b00000100 $
1%
b00000100 (
b00000100 )
#80000000
0!
0%
#90000000
1!
b00000101 $
1%
b00000101 (
b00000101 )
#100000000
0!
0%
#110000000
1!
b00000110 $
1%
b00000110 (
b00000110 )
#120000000
0!
0%
#130000000
1!
b00000111 $
1%
b00000111 (
b00000111 )
#140000000
0!
0%
#150000000
1!
b00001000 $
1%
b00001000 (
b00001000 )
#160000000
0!
0%
#170000000
1!
b00001001 $
1%
b00001001 (
b00001001 )
#180000000
0!
0%
#190000000
1!
b00001010 $
1%
b00001010 (
b00001010 )
#200000000
0!
0%
#210000000
1!
b00001011 $
1%
b00001011 (
b00001011 )
#220000000
0!
0%
#230000000
1!
b00001100 $
1%
b00001100 (
b00001100 )
#240000000
0!
0%
#250000000
1!
b00001101 $
1%
b00001101 (
b00001101 )
#260000000
0!
0%
#270000000
1!
b00001110 $
1%
b00001110 (
b00001110 )
#280000000
0!
0%
#290000000
1!
b00001111 $
1%
b00001111 (
b00001111 )
#300000000
0!
0%
#310000000
1!
b00010000 $
1%
b00010000 (
b00010000 )
#320000000
0!
0%
#330000000
1!
b00010001 $
1%
b00010001 (
b00010001 )
#340000000
0!
0%
#350000000
1!
b00010010 $
1%
b00010010 (
b00010010 )
#360000000
0!
0%
#370000000
1!
b00010011 $
1%
b00010011 (
b00010011 )
#380000000
0!
0%
#390000000
1!
b00010100 $
1%
b00010100 (
b00010100 )
#400000000
0!
0%
#410000000
1!
b00010101 $
1%
b00010101 (
b00010101 )
#420000000
0!
0%
#430000000
1!
b00010110 $
1%
b00010110 (
b00010110 )
#440000000
0!
0%
#450000000
1!
b00010111 $
1%
b00010111 (
b00010111 )
#460000000
0!
0%
#470000000
1!
b00011000 $
1%
b00011000 (
b00011000 )
#480000000
0!
0%
#490000000
1!
b00011001 $
1%
b00011001 (
b00011001 )
#500000000
0!
0%
#510000000
1!
b00011010 $
1%
b00011010 (
b00011010 )
#520000000
0!
0%
#530000000
1!
b00011011 $
1%
b00011011 (
b00011011 )
#540000000
0!
0%
#550000000
1!
b00011100 $
1%
b00011100 (
b00011100 )
#560000000
0!
0%
#570000000
1!
b00011101 $
1%
b00011101 (
b00011101 )
#580000000
0!
0%
#590000000
1!
b00011110 $
1%
b00011110 (
b00011110 )
#600000000
0!
0%
#610000000
1!
b00011111 $
1%
b00011111 (
b00011111 )
#620000000
0!
0%
#630000000
1!
1"
b00000000 $
1%
1&
b00000000 (
b00000000 )
#640000000
0!
0%
#650000000
1!
0"
b00000001 $
1%
0&
b00000001 (
b00000001 )
#660000000
0!
0%
#670000000
1!
b00000010 $
1%
b00000010 (
b00000010 )
#680000000
0!
0%
#690000000
1!
b00000011 $
1%
b00000011 (
b00000011 )
#700000000
0!
0%
#710000000
1!
b00000100 $
1%
b00000100 (
b00000100 )
#720000000
0!
0%
#730000000
1!
b00000101 $
1%
b00000101 (
b00000101 )
#740000000
0!
0%
#750000000
1!
b00000110 $
1%
b00000110 (
b00000110 )
#760000000
0!
0%
#770000000
1!
b00000111 $
1%
b00000111 (
b00000111 )
#780000000
0!
0%
#790000000
1!
b00001000 $
1%
b00001000 (
b00001000 )
#800000000
0!
0%
#810000000
1!
b00001001 $
1%
b00001001 (
b00001001 )
#820000000
0!
0%
#830000000
1!
b00001010 $
1%
b00001010 (
b00001010 )
#840000000
0!
0%
#850000000
1!
b00001011 $
1%
b00001011 (
b00001011 )
#860000000
0!
0%
#870000000
1!
b00001100 $
1%
b00001100 (
b00001100 )
#880000000
0!
0%
#890000000
1!
b00001101 $
1%
b00001101 (
b00001101 )
#900000000
0!
0%
#910000000
1!
b00001110 $
1%
b00001110 (
b00001110 )
#920000000
0!
0%
#930000000
1!
b00001111 $
1%
b00001111 (
b00001111 )
#940000000
0!
0%
#950000000
1!
b00010000 $
1%
b00010000 (
b00010000 )
#960000000
0!
0%
#970000000
1!
b00010001 $
1%
b00010001 (
b00010001 )
#980000000
0!
0%
#990000000
1!
b00010010 $
1%
b00010010 (
b00010010 )
#1000000000
0!
0%
#1010000000
1!
b00010011 $
1%
b00010011 (
b00010011 )
#1020000000
0!
0%
#1030000000
1!
b00010100 $
1%
b00010100 (
b00010100 )
#1040000000
0!
0%
#1050000000
1!
b00010101 $
1%
b00010101 (
b00010101 )
#1060000000
0!
0%
#1070000000
1!
b00010110 $
1%
b00010110 (
b00010110 )
#1080000000
0!
0%
#1090000000
1!
b00010111 $
1%
b00010111 (
b00010111 )
#1100000000
0!
0%
#1110000000
1!
b00011000 $
1%
b00011000 (
b00011000 )
#1120000000
0!
0%
#1130000000
1!
b00011001 $
1%
b00011001 (
b00011001 )
#1140000000
0!
0%
#1150000000
1!
b00011010 $
1%
b00011010 (
b00011010 )
#1160000000
0!
0%
#1170000000
1!
b00011011 $
1%
b00011011 (
b00011011 )
#1180000000
0!
0%
#1190000000
1!
b00011100 $
1%
b00011100 (
b00011100 )
#1200000000
0!
0%
#1210000000
1!
b00011101 $
1%
b00011101 (
b00011101 )
#1220000000
0!
0%
#1230000000
1!
b00011110 $
1%
b00011110 (
b00011110 )
#1240000000
0!
0%
#1250000000
1!
b00011111 $
1%
b00011111 (
b00011111 )
