counter/counter.vhd
library ieee;
use ieee.std_logic_1164.all;
use ieee.numeric_std.all;

entity counter is
  port (
    clk : in  std_logic;
    reset : in std_logic;
    enable : in std_logic;
    number: out std_logic_vector(7 downto 0)
  );
end entity counter;

architecture rtl of counter is
  signal num: unsigned(7 downto 0) := (others => '0');

begin
  process (clk)
    begin
      if rising_edge(clk) then
        if reset = '1' then
          num <= (others => '0');
        elsif enable = '1' then
          num <= num + 1;
        end if;
      end if;

  end process;

  number <= std_logic_vector(num);

end architecture rtl;

counter/tb_counter.vhd
library ieee;
use ieee.std_logic_1164.all;
use ieee.numeric_std.all;

entity tb_counter is
end entity tb_counter;

architecture sim of tb_counter is

  signal clk: std_logic := '0';
  signal reset: std_logic := '0';
  signal enable: std_logic := '0';
  signal counter : std_logic_vector(7 downto 0);

begin

  dut : entity work.counter
    port map (
      clk => clk,
      number => counter,
      reset => reset,
      enable => enable
    );

  stimulus : process
  begin
    enable <= '1';
    wait for 10 ns;

    for i in 0 to 5 loop
      clk <= '1';
      wait for 10 ns;
      clk <= '0';
      wait for 10 ns;
    end loop;

    reset <= '1';
    clk <= '1';
    wait for 10 ns;
    clk <= '0';
    wait for 10 ns;
    reset <= '0';

    -- for i in 0 to 30 loop
    --   clk <= '1';
    --   wait for 10 ns;
    --   clk <= '0';
    --   wait for 10 ns;
    -- end loop;

    wait;

  end process;


end architecture sim;

counter/tb_counter.vcd
$date
  Mon Aug 24 15:49:43 2026
$end
$version
  GHDL v0
$end
$timescale
  1 fs
$end
$scope module standard $end
$upscope $end
$scope module textio $end
$upscope $end
$scope module std_logic_1164 $end
$upscope $end
$scope module numeric_std $end
$upscope $end
$scope module tb_counter $end
$var reg 1 ! clk $end
$var reg 1 " reset $end
$var reg 1 # enable $end
$var reg 8 $ counter[7:0] $end
$scope module dut $end
$var reg 1 % clk $end
$var reg 1 & reset $end
$var reg 1 ' enable $end
$var reg 8 ( number[7:0] $end
$var reg 8 ) num[7:0] $end
$upscope $end
$upscope $end
$enddefinitions $end
#0
0!
0"
1#
b00000000 $
0%
0&
1'
b00000000 (
b00000000 )
#10000000
1!
b00000001 $
1%
b00000001 (
b00000001 )
#20000000
0!
0%
#30000000
1!
b00000010 $
1%
b00000010 (
b00000010 )
#40000000
0!
0%
#50000000
1!
b00000011 $
1%
b00000011 (
b00000011 )
#60000000
0!
0%
#70000000
1!
b00000100 $
1%
b00000100 (
b00000100 )
#80000000
0!
0%
#90000000
1!
b00000101 $
1%
b00000101 (
b00000101 )
#100000000
0!
0%
#110000000
1!
b00000110 $
1%
b00000110 (
b00000110 )
#120000000
0!
0%
#130000000
1!
1"
b00000000 $
1%
1&
b00000000 (
b00000000 )
#140000000
0!
0%
#150000000
0"
0&
