uart/shift_register.vhd
library ieee;
use ieee.std_logic_1164.all;
use ieee.numeric_std.all;

entity shift_register is
  port (
      clk: in std_logic;
      shift_input: in std_logic;
      shift_output: out std_logic;
      reset: in std_logic := '0';
      enable: in std_logic := '0';
      buf: buffer std_logic_vector(7 downto 0) := (others => '0');
      set: in std_logic := '0';
      buf_in: in std_logic_vector(7 downto 0) := (others => '0');
      get: in std_logic := '0';
      buf_out: out std_logic_vector(7 downto 0) := (others => '0')
      
  );
end entity shift_register;

architecture rtl of shift_register is

begin
    process(clk)
      begin
        if rising_edge(clk) then
          if reset = '1' then
            buf <= (others => '0');
            shift_output <= '0';
          elsif set = '1' then 
            buf <= buf_in;
          elsif get = '1' then 
            buf_out <= buf;
          elsif enable = '1' then 
            buf <= buf(6 downto 0) & shift_input;
            shift_output <= buf(7);
          end if;
        end if;

      end process;

end architecture rtl;

uart/uart_receiver.vhd
library ieee;
use ieee.std_logic_1164.all;
use ieee.numeric_std.all;

entity uart_receiver is
  port (
      clk: in std_logic;
      serial_in: in std_logic;
      shift_register_reset: buffer std_logic := '0';
      shift_register_enable: buffer std_logic := '0';
      shift_register_input: buffer std_logic;
      shift_register_output: buffer std_logic := '0';
      done: out std_logic := '0'

  );
end entity uart_receiver;

architecture rtl of uart_receiver is

  type state_t is (IDLE, START, DATA, STOP);
  signal state: state_t := IDLE;
  signal time_counter: unsigned(7 downto 0) := (others => '0');
  signal bits_sent_counter: unsigned(7 downto 0) := (others => '0');
  signal set:  std_logic := '0';
  signal buf_in:  std_logic_vector(7 downto 0) := (others => '0');
  signal get:  std_logic := '0';
  signal buf_out:  std_logic_vector(7 downto 0) := (others => '0');

begin

  shift_register : entity work.shift_register
    port map (
      clk => clk,
      shift_input => serial_in, 
      shift_output => shift_register_output, 
      reset => shift_register_reset,
      enable => shift_register_enable,
      get => done,
      buf_out => buf_out
    );

    process(clk)
      begin

        if rising_edge(clk) then
        if state = IDLE then

          done <= '0';
          if serial_in = '0' then
            state <= START;
            shift_register_reset <= '1';
            time_counter <= (others => '0');
          end if;

        elsif state = START then

          if time_counter = 12 then 
            time_counter <= (others => '0');
            state <= DATA;
          else 
            shift_register_reset <= '0';
            time_counter <= time_counter + 1;
          end if;

        elsif state = DATA then

            time_counter <= time_counter +1;

            if bits_sent_counter < 8 then 
              if time_counter = 0 then
                shift_register_enable <= '1';
                shift_register_input <= serial_in;

              elsif time_counter >= 10 then
                bits_sent_counter <= bits_sent_counter + 1;
                time_counter <= (others => '0');
              else
                shift_register_enable <= '0';
              end if;

            else
                state <= STOP;
                done <= '1';
                time_counter <= (others => '0');
            end if;

        elsif state = STOP then

          done <= '0';
          if time_counter = 5 then 
            time_counter <= (others => '0');
            state <= IDLE;
          else 
            time_counter <= time_counter + 1;
          end if;

        end if;

      end if;

    end process;
end architecture rtl;

uart/uart_sender.vhd
library ieee;
use ieee.std_logic_1164.all;
use ieee.numeric_std.all;


entity uart_sender is
  port (
      clk: in std_logic;
      serial_out: out std_logic := '1';
      send: in std_logic;
      shift_register_reset: buffer std_logic := '0';
      shift_register_enable: buffer std_logic := '0';
      shift_register_input: buffer std_logic := '0';
      shift_register_output: buffer std_logic;
      set: in std_logic := '0';
      buf_in: in  std_logic_vector(7 downto 0) := (others => '0');
      get: in std_logic := '0';
      buf_out: out  std_logic_vector(7 downto 0) := (others => '0')
      
  );
end entity uart_sender;

architecture rtl of uart_sender is

  type state_t is (IDLE, START, DATA, STOP);
  signal state: state_t := IDLE;
  signal time_counter: unsigned(7 downto 0) := (others => '0');
  signal bits_sent_counter: unsigned(7 downto 0) := (others => '0');
  
  -- State 1 - make it possible to read values into you - when you get the signal to send something switch into state 2
  -- State 2 - send over the bits one by one and go back to state 1
begin

      -- clk: in std_logic;
      -- shift_input: in std_logic;
      -- shift_output: out std_logic;
      -- reset: in std_logic := '0';
      -- enable: in std_logic := '0';

  shift_register : entity work.shift_register
    port map (
      clk => clk,
      shift_input => shift_register_input, 
      shift_output => shift_register_output, 
      reset => shift_register_reset,
      enable => shift_register_enable,
      set => set,
      buf_in => buf_in,
      get => get,
      buf_out => buf_out
    );

    process(clk)
      begin
        if rising_edge(clk) then
          if state = IDLE then
            serial_out <= '1';
            if send = '1' then 
              state <= START;
              time_counter <= (others => '0');
            end if;

          elsif state = START then
            if time_counter = 0 then
              serial_out <= '0';
              time_counter <= time_counter +1;
            elsif time_counter >= 9 then  
              state <= DATA;
              time_counter <= (others => '0');
              bits_sent_counter <= (others => '0');
              shift_register_enable <= '1';
            else 
              time_counter <= time_counter +1;
            end if;


          elsif state = DATA then 

            time_counter <= time_counter +1;

            if bits_sent_counter < 8 then 

              if time_counter = 0 then
                shift_register_enable <= '0';
              elsif time_counter >= 10 then
                -- bit sent here 
                bits_sent_counter <= bits_sent_counter + 1;
                shift_register_enable <= '1';
                time_counter <= (others => '0');
              else
                serial_out <= shift_register_output;
              end if;

            else
                state <= STOP;
            end if;



          elsif state = STOP then 
            serial_out <= '1';
            time_counter <= time_counter +1;
            if time_counter >= 10 then 
              state <= IDLE;
            end if;
          end if ;
          

        end if;

      end process;

end architecture rtl;

uart/tb_uart.vhd
library ieee;
use ieee.std_logic_1164.all;
use ieee.numeric_std.all;

entity tb_uart is
end entity tb_uart;

architecture sim of tb_uart is

      signal clk:  std_logic := '0';
      signal serial: std_logic;
      signal done: std_logic := '0';
      signal send: std_logic := '0';

      signal set:  std_logic := '0';
      signal buf_sender: std_logic_vector(7 downto 0);
      signal buf_receiver: std_logic_vector(7 downto 0);
begin

  sender : entity work.uart_sender
    port map (
      clk => clk,
      serial_out => serial,
      send => send,
      buf_in => buf_sender,
      set => set
    );
    
  receiver : entity work.uart_receiver
    port map (
      clk => clk,
      serial_in => serial,
      done => done
    );

  stimulus : process
  begin
    
    buf_sender <= "10101010";
    set <= '1';

    wait for 10 ns;
    clk <= '1';
    wait for 10 ns;
    clk <= '0';

    wait for 10 ns;
    set <= '0';

    wait for 10 ns;

    send <= '1';
    wait for 10 ns;
    clk <= '1';
    wait for 10 ns;
    clk <= '0';
    wait for 10 ns;
    send <= '0';

    while done = '0' loop
      clk <= '1';
      wait for 10 ns;
      clk <= '0';
      wait for 10 ns;
    end loop;


    wait;

  end process;

end architecture sim;

uart/tb_uart.vcd
$date
  Tue Aug 25 20:06:22 2026
$end
$version
  GHDL v0
$end
$timescale
  1 fs
$end
$scope module standard $end
$upscope $end
$scope module textio $end
$upscope $end
$scope module std_logic_1164 $end
$upscope $end
$scope module numeric_std $end
$upscope $end
$scope module tb_uart $end
$var reg 1 ! clk $end
$var reg 1 " serial $end
$var reg 1 # done $end
$var reg 1 $ send $end
$var reg 1 % set $end
$var reg 8 & buf_sender[7:0] $end
$var reg 8 ' buf_receiver[7:0] $end
$scope module sender $end
$var reg 1 ( clk $end
$var reg 1 ) serial_out $end
$var reg 1 * send $end
$var reg 1 + shift_register_reset $end
$var reg 1 , shift_register_enable $end
$var reg 1 - shift_register_input $end
$var reg 1 . shift_register_output $end
$var reg 1 / set $end
$var reg 8 0 buf_in[7:0] $end
$var reg 1 1 get $end
$var reg 8 2 buf_out[7:0] $end
$comment state is not handled $end
$var reg 8 3 time_counter[7:0] $end
$var reg 8 4 bits_sent_counter[7:0] $end
$scope module shift_register $end
$var reg 1 5 clk $end
$var reg 1 6 shift_input $end
$var reg 1 7 shift_output $end
$var reg 1 8 reset $end
$var reg 1 9 enable $end
$var reg 8 : buf[7:0] $end
$var reg 1 ; set $end
$var reg 8 < buf_in[7:0] $end
$var reg 1 = get $end
$var reg 8 > buf_out[7:0] $end
$upscope $end
$upscope $end
$scope module receiver $end
$var reg 1 ? clk $end
$var reg 1 @ serial_in $end
$var reg 1 A shift_register_reset $end
$var reg 1 B shift_register_enable $end
$var reg 1 C shift_register_input $end
$var reg 1 D shift_register_output $end
$var reg 1 E done $end
$comment state is not handled $end
$var reg 8 F time_counter[7:0] $end
$var reg 8 G bits_sent_counter[7:0] $end
$var reg 1 H set $end
$var reg 8 I buf_in[7:0] $end
$var reg 1 J get $end
$var reg 8 K buf_out[7:0] $end
$scope module shift_register $end
$var reg 1 L clk $end
$var reg 1 M shift_input $end
$var reg 1 N shift_output $end
$var reg 1 O reset $end
$var reg 1 P enable $end
$var reg 8 Q buf[7:0] $end
$var reg 1 R set $end
$var reg 8 S buf_in[7:0] $end
$var reg 1 T get $end
$var reg 8 U buf_out[7:0] $end
$upscope $end
$upscope $end
$upscope $end
$enddefinitions $end
#0
0!
1"
0#
0$
1%
b10101010 &
bUUUUUUUU '
0(
1)
0*
0+
0,
0-
U.
1/
b10101010 0
01
b00000000 2
b00000000 3
b00000000 4
05
06
U7
08
09
b00000000 :
1;
b10101010 <
0=
b00000000 >
0?
1@
0A
0B
UC
UD
0E
b00000000 F
b00000000 G
0H
b00000000 I
0J
b00000000 K
0L
1M
UN
0O
0P
b00000000 Q
0R
b00000000 S
0T
b00000000 U
#10000000
1!
1(
15
b10101010 :
1?
1L
#20000000
0!
0(
05
0?
0L
#30000000
0%
0/
0;
#40000000
1$
1*
#50000000
1!
1(
15
1?
1L
#60000000
0!
0(
05
0?
0L
#70000000
1!
0"
0$
1(
0)
0*
b00000001 3
15
1?
0@
1L
0M
#80000000
0!
0(
05
0?
0L
#90000000
1!
1(
b00000010 3
15
1?
1A
1L
1O
#100000000
0!
0(
05
0?
0L
#110000000
1!
1(
b00000011 3
15
1?
0A
0D
b00000001 F
1L
0N
0O
#120000000
0!
0(
05
0?
0L
#130000000
1!
1(
b00000100 3
15
1?
b00000010 F
1L
#140000000
0!
0(
05
0?
0L
#150000000
1!
1(
b00000101 3
15
1?
b00000011 F
1L
#160000000
0!
0(
05
0?
0L
#170000000
1!
1(
b00000110 3
15
1?
b00000100 F
1L
#180000000
0!
0(
05
0?
0L
#190000000
1!
1(
b00000111 3
15
1?
b00000101 F
1L
#200000000
0!
0(
05
0?
0L
#210000000
1!
1(
b00001000 3
15
1?
b00000110 F
1L
#220000000
0!
0(
05
0?
0L
#230000000
1!
1(
b00001001 3
15
1?
b00000111 F
1L
#240000000
0!
0(
05
0?
0L
#250000000
1!
1(
1,
b00000000 3
15
19
1?
b00001000 F
1L
#260000000
0!
0(
05
0?
0L
#270000000
1!
1(
0,
1.
b00000001 3
15
17
09
b01010100 :
1?
b00001001 F
1L
#280000000
0!
0(
05
0?
0L
#290000000
1!
1"
1(
1)
b00000010 3
15
1?
1@
b00001010 F
1L
1M
#300000000
0!
0(
05
0?
0L
#310000000
1!
1(
b00000011 3
15
1?
b00001011 F
1L
#320000000
0!
0(
05
0?
0L
#330000000
1!
1(
b00000100 3
15
1?
b00001100 F
1L
#340000000
0!
0(
05
0?
0L
#350000000
1!
1(
b00000101 3
15
1?
b00000000 F
1L
#360000000
0!
0(
05
0?
0L
#370000000
1!
1(
b00000110 3
15
1?
1B
1C
b00000001 F
1L
1P
#380000000
0!
0(
05
0?
0L
#390000000
1!
1(
b00000111 3
15
1?
0B
b00000010 F
1L
0P
b00000001 Q
#400000000
0!
0(
05
0?
0L
#410000000
1!
1(
b00001000 3
15
1?
b00000011 F
1L
#420000000
0!
0(
05
0?
0L
#430000000
1!
1(
b00001001 3
15
1?
b00000100 F
1L
#440000000
0!
0(
05
0?
0L
#450000000
1!
1(
b00001010 3
15
1?
b00000101 F
1L
#460000000
0!
0(
05
0?
0L
#470000000
1!
1(
1,
b00000000 3
b00000001 4
15
19
1?
b00000110 F
1L
#480000000
0!
0(
05
0?
0L
#490000000
1!
1(
0,
0.
b00000001 3
15
07
09
b10101000 :
1?
b00000111 F
1L
#500000000
0!
0(
05
0?
0L
#510000000
1!
0"
1(
0)
b00000010 3
15
1?
0@
b00001000 F
1L
0M
#520000000
0!
0(
05
0?
0L
#530000000
1!
1(
b00000011 3
15
1?
b00001001 F
1L
#540000000
0!
0(
05
0?
0L
#550000000
1!
1(
b00000100 3
15
1?
b00001010 F
1L
#560000000
0!
0(
05
0?
0L
#570000000
1!
1(
b00000101 3
15
1?
b00000000 F
b00000001 G
1L
#580000000
0!
0(
05
0?
0L
#590000000
1!
1(
b00000110 3
15
1?
1B
0C
b00000001 F
1L
1P
#600000000
0!
0(
05
0?
0L
#610000000
1!
1(
b00000111 3
15
1?
0B
b00000010 F
1L
0P
b00000010 Q
#620000000
0!
0(
05
0?
0L
#630000000
1!
1(
b00001000 3
15
1?
b00000011 F
1L
#640000000
0!
0(
05
0?
0L
#650000000
1!
1(
b00001001 3
15
1?
b00000100 F
1L
#660000000
0!
0(
05
0?
0L
#670000000
1!
1(
b00001010 3
15
1?
b00000101 F
1L
#680000000
0!
0(
05
0?
0L
#690000000
1!
1(
1,
b00000000 3
b00000010 4
15
19
1?
b00000110 F
1L
#700000000
0!
0(
05
0?
0L
#710000000
1!
1(
0,
1.
b00000001 3
15
17
09
b01010000 :
1?
b00000111 F
1L
#720000000
0!
0(
05
0?
0L
#730000000
1!
1"
1(
1)
b00000010 3
15
1?
1@
b00001000 F
1L
1M
#740000000
0!
0(
05
0?
0L
#750000000
1!
1(
b00000011 3
15
1?
b00001001 F
1L
#760000000
0!
0(
05
0?
0L
#770000000
1!
1(
b00000100 3
15
1?
b00001010 F
1L
#780000000
0!
0(
05
0?
0L
#790000000
1!
1(
b00000101 3
15
1?
b00000000 F
b00000010 G
1L
#800000000
0!
0(
05
0?
0L
#810000000
1!
1(
b00000110 3
15
1?
1B
1C
b00000001 F
1L
1P
#820000000
0!
0(
05
0?
0L
#830000000
1!
1(
b00000111 3
15
1?
0B
b00000010 F
1L
0P
b00000101 Q
#840000000
0!
0(
05
0?
0L
#850000000
1!
1(
b00001000 3
15
1?
b00000011 F
1L
#860000000
0!
0(
05
0?
0L
#870000000
1!
1(
b00001001 3
15
1?
b00000100 F
1L
#880000000
0!
0(
05
0?
0L
#890000000
1!
1(
b00001010 3
15
1?
b00000101 F
1L
#900000000
0!
0(
05
0?
0L
#910000000
1!
1(
1,
b00000000 3
b00000011 4
15
19
1?
b00000110 F
1L
#920000000
0!
0(
05
0?
0L
#930000000
1!
1(
0,
0.
b00000001 3
15
07
09
b10100000 :
1?
b00000111 F
1L
#940000000
0!
0(
05
0?
0L
#950000000
1!
0"
1(
0)
b00000010 3
15
1?
0@
b00001000 F
1L
0M
#960000000
0!
0(
05
0?
0L
#970000000
1!
1(
b00000011 3
15
1?
b00001001 F
1L
#980000000
0!
0(
05
0?
0L
#990000000
1!
1(
b00000100 3
15
1?
b00001010 F
1L
#1000000000
0!
0(
05
0?
0L
#1010000000
1!
1(
b00000101 3
15
1?
b00000000 F
b00000011 G
1L
#1020000000
0!
0(
05
0?
0L
#1030000000
1!
1(
b00000110 3
15
1?
1B
0C
b00000001 F
1L
1P
#1040000000
0!
0(
05
0?
0L
#1050000000
1!
1(
b00000111 3
15
1?
0B
b00000010 F
1L
0P
b00001010 Q
#1060000000
0!
0(
05
0?
0L
#1070000000
1!
1(
b00001000 3
15
1?
b00000011 F
1L
#1080000000
0!
0(
05
0?
0L
#1090000000
1!
1(
b00001001 3
15
1?
b00000100 F
1L
#1100000000
0!
0(
05
0?
0L
#1110000000
1!
1(
b00001010 3
15
1?
b00000101 F
1L
#1120000000
0!
0(
05
0?
0L
#1130000000
1!
1(
1,
b00000000 3
b00000100 4
15
19
1?
b00000110 F
1L
#1140000000
0!
0(
05
0?
0L
#1150000000
1!
1(
0,
1.
b00000001 3
15
17
09
b01000000 :
1?
b00000111 F
1L
#1160000000
0!
0(
05
0?
0L
#1170000000
1!
1"
1(
1)
b00000010 3
15
1?
1@
b00001000 F
1L
1M
#1180000000
0!
0(
05
0?
0L
#1190000000
1!
1(
b00000011 3
15
1?
b00001001 F
1L
#1200000000
0!
0(
05
0?
0L
#1210000000
1!
1(
b00000100 3
15
1?
b00001010 F
1L
#1220000000
0!
0(
05
0?
0L
#1230000000
1!
1(
b00000101 3
15
1?
b00000000 F
b00000100 G
1L
#1240000000
0!
0(
05
0?
0L
#1250000000
1!
1(
b00000110 3
15
1?
1B
1C
b00000001 F
1L
1P
#1260000000
0!
0(
05
0?
0L
#1270000000
1!
1(
b00000111 3
15
1?
0B
b00000010 F
1L
0P
b00010101 Q
#1280000000
0!
0(
05
0?
0L
#1290000000
1!
1(
b00001000 3
15
1?
b00000011 F
1L
#1300000000
0!
0(
05
0?
0L
#1310000000
1!
1(
b00001001 3
15
1?
b00000100 F
1L
#1320000000
0!
0(
05
0?
0L
#1330000000
1!
1(
b00001010 3
15
1?
b00000101 F
1L
#1340000000
0!
0(
05
0?
0L
#1350000000
1!
1(
1,
b00000000 3
b00000101 4
15
19
1?
b00000110 F
1L
#1360000000
0!
0(
05
0?
0L
#1370000000
1!
1(
0,
0.
b00000001 3
15
07
09
b10000000 :
1?
b00000111 F
1L
#1380000000
0!
0(
05
0?
0L
#1390000000
1!
0"
1(
0)
b00000010 3
15
1?
0@
b00001000 F
1L
0M
#1400000000
0!
0(
05
0?
0L
#1410000000
1!
1(
b00000011 3
15
1?
b00001001 F
1L
#1420000000
0!
0(
05
0?
0L
#1430000000
1!
1(
b00000100 3
15
1?
b00001010 F
1L
#1440000000
0!
0(
05
0?
0L
#1450000000
1!
1(
b00000101 3
15
1?
b00000000 F
b00000101 G
1L
#1460000000
0!
0(
05
0?
0L
#1470000000
1!
1(
b00000110 3
15
1?
1B
0C
b00000001 F
1L
1P
#1480000000
0!
0(
05
0?
0L
#1490000000
1!
1(
b00000111 3
15
1?
0B
b00000010 F
1L
0P
b00101010 Q
#1500000000
0!
0(
05
0?
0L
#1510000000
1!
1(
b00001000 3
15
1?
b00000011 F
1L
#1520000000
0!
0(
05
0?
0L
#1530000000
1!
1(
b00001001 3
15
1?
b00000100 F
1L
#1540000000
0!
0(
05
0?
0L
#1550000000
1!
1(
b00001010 3
15
1?
b00000101 F
1L
#1560000000
0!
0(
05
0?
0L
#1570000000
1!
1(
1,
b00000000 3
b00000110 4
15
19
1?
b00000110 F
1L
#1580000000
0!
0(
05
0?
0L
#1590000000
1!
1(
0,
1.
b00000001 3
15
17
09
b00000000 :
1?
b00000111 F
1L
#1600000000
0!
0(
05
0?
0L
#1610000000
1!
1"
1(
1)
b00000010 3
15
1?
1@
b00001000 F
1L
1M
#1620000000
0!
0(
05
0?
0L
#1630000000
1!
1(
b00000011 3
15
1?
b00001001 F
1L
#1640000000
0!
0(
05
0?
0L
#1650000000
1!
1(
b00000100 3
15
1?
b00001010 F
1L
#1660000000
0!
0(
05
0?
0L
#1670000000
1!
1(
b00000101 3
15
1?
b00000000 F
b00000110 G
1L
#1680000000
0!
0(
05
0?
0L
#1690000000
1!
1(
b00000110 3
15
1?
1B
1C
b00000001 F
1L
1P
#1700000000
0!
0(
05
0?
0L
#1710000000
1!
1(
b00000111 3
15
1?
0B
b00000010 F
1L
0P
b01010101 Q
#1720000000
0!
0(
05
0?
0L
#1730000000
1!
1(
b00001000 3
15
1?
b00000011 F
1L
#1740000000
0!
0(
05
0?
0L
#1750000000
1!
1(
b00001001 3
15
1?
b00000100 F
1L
#1760000000
0!
0(
05
0?
0L
#1770000000
1!
1(
b00001010 3
15
1?
b00000101 F
1L
#1780000000
0!
0(
05
0?
0L
#1790000000
1!
1(
1,
b00000000 3
b00000111 4
15
19
1?
b00000110 F
1L
#1800000000
0!
0(
05
0?
0L
#1810000000
1!
1(
0,
0.
b00000001 3
15
07
09
1?
b00000111 F
1L
#1820000000
0!
0(
05
0?
0L
#1830000000
1!
0"
1(
0)
b00000010 3
15
1?
0@
b00001000 F
1L
0M
#1840000000
0!
0(
05
0?
0L
#1850000000
1!
1(
b00000011 3
15
1?
b00001001 F
1L
#1860000000
0!
0(
05
0?
0L
#1870000000
1!
1(
b00000100 3
15
1?
b00001010 F
1L
#1880000000
0!
0(
05
0?
0L
#1890000000
1!
1(
b00000101 3
15
1?
b00000000 F
b00000111 G
1L
#1900000000
0!
0(
05
0?
0L
#1910000000
1!
1(
b00000110 3
15
1?
1B
0C
b00000001 F
1L
1P
#1920000000
0!
0(
05
0?
0L
#1930000000
1!
1(
b00000111 3
15
1?
0B
b00000010 F
1L
0P
b10101010 Q
#1940000000
0!
0(
05
0?
0L
#1950000000
1!
1(
b00001000 3
15
1?
b00000011 F
1L
#1960000000
0!
0(
05
0?
0L
#1970000000
1!
1(
b00001001 3
15
1?
b00000100 F
1L
#1980000000
0!
0(
05
0?
0L
#1990000000
1!
1(
b00001010 3
15
1?
b00000101 F
1L
#2000000000
0!
0(
05
0?
0L
#2010000000
1!
1(
1,
b00000000 3
b00001000 4
15
19
1?
b00000110 F
1L
#2020000000
0!
0(
05
0?
0L
#2030000000
1!
1(
b00000001 3
15
1?
b00000111 F
1L
#2040000000
0!
0(
05
0?
0L
#2050000000
1!
1"
1(
1)
b00000010 3
15
1?
1@
b00001000 F
1L
1M
#2060000000
0!
0(
05
0?
0L
#2070000000
1!
1(
b00000011 3
15
1?
b00001001 F
1L
#2080000000
0!
0(
05
0?
0L
#2090000000
1!
1(
b00000100 3
15
1?
b00001010 F
1L
#2100000000
0!
0(
05
0?
0L
#2110000000
1!
1(
b00000101 3
15
1?
b00000000 F
b00001000 G
1L
#2120000000
0!
0(
05
0?
0L
#2130000000
1!
1#
1(
b00000110 3
15
1?
1E
1L
1T
