uart/shift_register.vhd
library ieee;
use ieee.std_logic_1164.all;
use ieee.numeric_std.all;

entity shift_register is
  port (
      clk: in std_logic;
      shift_input: in std_logic;
      shift_output: out std_logic;
      reset: in std_logic := '0';
      enable: in std_logic := '0';
      buf: buffer std_logic_vector(7 downto 0) := "11100101"
  );
end entity shift_register;

architecture rtl of shift_register is

begin
    process(clk)
      begin
        if rising_edge(clk) then
          if reset = '1' then
            buf <= (others => '0');
            shift_output <= '0';
          elsif enable = '1' then 
            buf <= buf(6 downto 0) & shift_input;
            shift_output <= buf(7);
          end if;
        end if;

      end process;

end architecture rtl;

uart/uart_receiver.vhd
library ieee;
use ieee.std_logic_1164.all;
use ieee.numeric_std.all;

entity uart_receiver is
  port (
      clk: in std_logic;
      serial_in: in std_logic;
      shift_register_reset: buffer std_logic := '0';
      shift_register_enable: buffer std_logic := '1';
      shift_register_input: buffer std_logic;
      shift_register_output: buffer std_logic := '0'
  );
end entity uart_receiver;

architecture rtl of uart_receiver is

begin

  shift_register : entity work.shift_register
    port map (
      clk => clk,
      shift_input => serial_in, 
      shift_output => shift_register_output, 
      reset => shift_register_reset,
      enable => shift_register_enable
    );
  -- so i have 2 states
  -- State 1 -> wait for a low on the wire then sync clock and switch state
  -- State 2 -> read current bit into the shift register until you got 8 and switch an "im done bit" and go back to the state 1
  -- TODO: add your logic here

  shift_register_input <= serial_in;

end architecture rtl;

uart/uart_sender.vhd
library ieee;
use ieee.std_logic_1164.all;
use ieee.numeric_std.all;


entity uart_sender is
  port (
      clk: in std_logic;
      serial_out: out std_logic := '1';
      send: in std_logic;
      shift_register_reset: buffer std_logic := '0';
      shift_register_enable: buffer std_logic := '0';
      shift_register_input: buffer std_logic := '0';
      shift_register_output: buffer std_logic
      
  );
end entity uart_sender;

architecture rtl of uart_sender is

  type state_t is (IDLE, START, DATA, STOP);
  signal state: state_t := IDLE;
  signal time_counter: unsigned(7 downto 0) := (others => '0');
  signal bits_sent_counter: unsigned(7 downto 0) := (others => '0');
  -- State 1 - make it possible to read values into you - when you get the signal to send something switch into state 2
  -- State 2 - send over the bits one by one and go back to state 1
begin

      -- clk: in std_logic;
      -- shift_input: in std_logic;
      -- shift_output: out std_logic;
      -- reset: in std_logic := '0';
      -- enable: in std_logic := '0';

  shift_register : entity work.shift_register
    port map (
      clk => clk,
      shift_input => shift_register_input, 
      shift_output => shift_register_output, 
      reset => shift_register_reset,
      enable => shift_register_enable
    );

    process(clk)
      begin
        if rising_edge(clk) then
          if state = IDLE then
            serial_out <= '1';
            if send = '1' then 
              state <= START;
              time_counter <= (others => '0');
            end if;

          elsif state = START then
            if time_counter = 0 then
              serial_out <= '0';
              time_counter <= time_counter +1;
            elsif time_counter >= 9 then  
              state <= DATA;
              time_counter <= (others => '0');
              bits_sent_counter <= (others => '0');
              shift_register_enable <= '1';
            else 
              time_counter <= time_counter +1;
            end if;


          elsif state = DATA then 

            time_counter <= time_counter +1;

            if bits_sent_counter < 8 then 

              if time_counter = 0 then
                shift_register_enable <= '0';
              elsif time_counter >= 10 then
                -- bit sent here 
                bits_sent_counter <= bits_sent_counter + 1;
                shift_register_enable <= '1';
                time_counter <= (others => '0');
              else
                serial_out <= shift_register_output;
              end if;

            else
                state <= STOP;
            end if;



          elsif state = STOP then 
            serial_out <= '1';
            time_counter <= time_counter +1;
            if time_counter >= 10 then 
              state <= IDLE;
            end if;
          end if ;
          

        end if;

      end process;

end architecture rtl;

uart/tb_uart.vhd
library ieee;
use ieee.std_logic_1164.all;
use ieee.numeric_std.all;

entity tb_uart is
end entity tb_uart;

architecture sim of tb_uart is

      signal clk:  std_logic := '0';
      signal serial: std_logic;
      signal send: std_logic := '0';

begin

  sender : entity work.uart_sender
    port map (
      clk => clk,
      serial_out => serial,
      send => send
    );
    
  receiver : entity work.uart_receiver
    port map (
      clk => clk,
      serial_in => serial
    );

  stimulus : process
  begin
    wait for 10 ns;

    send <= '1';
    wait for 10 ns;

    for i in 0 to 300 loop
      clk <= '1';
      wait for 10 ns;
      clk <= '0';
      wait for 10 ns;
    end loop;

    wait;

  end process;

end architecture sim;

uart/tb_uart.vcd
$date
  Tue Aug 25 18:22:23 2026
$end
$version
  GHDL v0
$end
$timescale
  1 fs
$end
$scope module standard $end
$upscope $end
$scope module textio $end
$upscope $end
$scope module std_logic_1164 $end
$upscope $end
$scope module numeric_std $end
$upscope $end
$scope module tb_uart $end
$var reg 1 ! clk $end
$var reg 1 " serial $end
$var reg 1 # send $end
$scope module sender $end
$var reg 1 $ clk $end
$var reg 1 % serial_out $end
$var reg 1 & send $end
$var reg 1 ' shift_register_reset $end
$var reg 1 ( shift_register_enable $end
$var reg 1 ) shift_register_input $end
$var reg 1 * shift_register_output $end
$comment state is not handled $end
$var reg 8 + time_counter[7:0] $end
$var reg 8 , bits_sent_counter[7:0] $end
$scope module shift_register $end
$var reg 1 - clk $end
$var reg 1 . shift_input $end
$var reg 1 / shift_output $end
$var reg 1 0 reset $end
$var reg 1 1 enable $end
$var reg 8 2 buf[7:0] $end
$upscope $end
$upscope $end
$scope module receiver $end
$var reg 1 3 clk $end
$var reg 1 4 serial_in $end
$var reg 1 5 shift_register_reset $end
$var reg 1 6 shift_register_enable $end
$var reg 1 7 shift_register_input $end
$var reg 1 8 shift_register_output $end
$scope module shift_register $end
$var reg 1 9 clk $end
$var reg 1 : shift_input $end
$var reg 1 ; shift_output $end
$var reg 1 < reset $end
$var reg 1 = enable $end
$var reg 8 > buf[7:0] $end
$upscope $end
$upscope $end
$upscope $end
$enddefinitions $end
#0
0!
1"
0#
0$
1%
0&
0'
0(
0)
U*
b00000000 +
b00000000 ,
0-
0.
U/
00
01
b11100101 2
03
14
05
16
17
U8
09
1:
U;
0<
1=
b11100101 >
#10000000
1#
1&
#20000000
1!
1$
1-
13
18
19
1;
b11001011 >
#30000000
0!
0$
0-
03
09
#40000000
1!
0"
1$
0%
b00000001 +
1-
13
04
07
19
0:
b10010111 >
#50000000
0!
0$
0-
03
09
#60000000
1!
1$
b00000010 +
1-
13
19
b00101110 >
#70000000
0!
0$
0-
03
09
#80000000
1!
1$
b00000011 +
1-
13
08
19
0;
b01011100 >
#90000000
0!
0$
0-
03
09
#100000000
1!
1$
b00000100 +
1-
13
19
b10111000 >
#110000000
0!
0$
0-
03
09
#120000000
1!
1$
b00000101 +
1-
13
18
19
1;
b01110000 >
#130000000
0!
0$
0-
03
09
#140000000
1!
1$
b00000110 +
1-
13
08
19
0;
b11100000 >
#150000000
0!
0$
0-
03
09
#160000000
1!
1$
b00000111 +
1-
13
18
19
1;
b11000000 >
#170000000
0!
0$
0-
03
09
#180000000
1!
1$
b00001000 +
1-
13
19
b10000000 >
#190000000
0!
0$
0-
03
09
#200000000
1!
1$
b00001001 +
1-
13
19
b00000000 >
#210000000
0!
0$
0-
03
09
#220000000
1!
1$
1(
b00000000 +
1-
11
13
08
19
0;
#230000000
0!
0$
0-
03
09
#240000000
1!
1$
0(
1*
b00000001 +
1-
1/
01
b11001010 2
13
19
#250000000
0!
0$
0-
03
09
#260000000
1!
1"
1$
1%
b00000010 +
1-
13
14
17
19
1:
#270000000
0!
0$
0-
03
09
#280000000
1!
1$
b00000011 +
1-
13
19
b00000001 >
#290000000
0!
0$
0-
03
09
#300000000
1!
1$
b00000100 +
1-
13
19
b00000011 >
#310000000
0!
0$
0-
03
09
#320000000
1!
1$
b00000101 +
1-
13
19
b00000111 >
#330000000
0!
0$
0-
03
09
#340000000
1!
1$
b00000110 +
1-
13
19
b00001111 >
#350000000
0!
0$
0-
03
09
#360000000
1!
1$
b00000111 +
1-
13
19
b00011111 >
#370000000
0!
0$
0-
03
09
#380000000
1!
1$
b00001000 +
1-
13
19
b00111111 >
#390000000
0!
0$
0-
03
09
#400000000
1!
1$
b00001001 +
1-
13
19
b01111111 >
#410000000
0!
0$
0-
03
09
#420000000
1!
1$
b00001010 +
1-
13
19
b11111111 >
#430000000
0!
0$
0-
03
09
#440000000
1!
1$
1(
b00000000 +
b00000001 ,
1-
11
13
18
19
1;
#450000000
0!
0$
0-
03
09
#460000000
1!
1$
0(
b00000001 +
1-
01
b10010100 2
13
19
#470000000
0!
0$
0-
03
09
#480000000
1!
1$
b00000010 +
1-
13
19
#490000000
0!
0$
0-
03
09
#500000000
1!
1$
b00000011 +
1-
13
19
#510000000
0!
0$
0-
03
09
#520000000
1!
1$
b00000100 +
1-
13
19
#530000000
0!
0$
0-
03
09
#540000000
1!
1$
b00000101 +
1-
13
19
#550000000
0!
0$
0-
03
09
#560000000
1!
1$
b00000110 +
1-
13
19
#570000000
0!
0$
0-
03
09
#580000000
1!
1$
b00000111 +
1-
13
19
#590000000
0!
0$
0-
03
09
#600000000
1!
1$
b00001000 +
1-
13
19
#610000000
0!
0$
0-
03
09
#620000000
1!
1$
b00001001 +
1-
13
19
#630000000
0!
0$
0-
03
09
#640000000
1!
1$
b00001010 +
1-
13
19
#650000000
0!
0$
0-
03
09
#660000000
1!
1$
1(
b00000000 +
b00000010 ,
1-
11
13
19
#670000000
0!
0$
0-
03
09
#680000000
1!
1$
0(
b00000001 +
1-
01
b00101000 2
13
19
#690000000
0!
0$
0-
03
09
#700000000
1!
1$
b00000010 +
1-
13
19
#710000000
0!
0$
0-
03
09
#720000000
1!
1$
b00000011 +
1-
13
19
#730000000
0!
0$
0-
03
09
#740000000
1!
1$
b00000100 +
1-
13
19
#750000000
0!
0$
0-
03
09
#760000000
1!
1$
b00000101 +
1-
13
19
#770000000
0!
0$
0-
03
09
#780000000
1!
1$
b00000110 +
1-
13
19
#790000000
0!
0$
0-
03
09
#800000000
1!
1$
b00000111 +
1-
13
19
#810000000
0!
0$
0-
03
09
#820000000
1!
1$
b00001000 +
1-
13
19
#830000000
0!
0$
0-
03
09
#840000000
1!
1$
b00001001 +
1-
13
19
#850000000
0!
0$
0-
03
09
#860000000
1!
1$
b00001010 +
1-
13
19
#870000000
0!
0$
0-
03
09
#880000000
1!
1$
1(
b00000000 +
b00000011 ,
1-
11
13
19
#890000000
0!
0$
0-
03
09
#900000000
1!
1$
0(
0*
b00000001 +
1-
0/
01
b01010000 2
13
19
#910000000
0!
0$
0-
03
09
#920000000
1!
0"
1$
0%
b00000010 +
1-
13
04
07
19
0:
#930000000
0!
0$
0-
03
09
#940000000
1!
1$
b00000011 +
1-
13
19
b11111110 >
#950000000
0!
0$
0-
03
09
#960000000
1!
1$
b00000100 +
1-
13
19
b11111100 >
#970000000
0!
0$
0-
03
09
#980000000
1!
1$
b00000101 +
1-
13
19
b11111000 >
#990000000
0!
0$
0-
03
09
#1000000000
1!
1$
b00000110 +
1-
13
19
b11110000 >
#1010000000
0!
0$
0-
03
09
#1020000000
1!
1$
b00000111 +
1-
13
19
b11100000 >
#1030000000
0!
0$
0-
03
09
#1040000000
1!
1$
b00001000 +
1-
13
19
b11000000 >
#1050000000
0!
0$
0-
03
09
#1060000000
1!
1$
b00001001 +
1-
13
19
b10000000 >
#1070000000
0!
0$
0-
03
09
#1080000000
1!
1$
b00001010 +
1-
13
19
b00000000 >
#1090000000
0!
0$
0-
03
09
#1100000000
1!
1$
1(
b00000000 +
b00000100 ,
1-
11
13
08
19
0;
#1110000000
0!
0$
0-
03
09
#1120000000
1!
1$
0(
b00000001 +
1-
01
b10100000 2
13
19
#1130000000
0!
0$
0-
03
09
#1140000000
1!
1$
b00000010 +
1-
13
19
#1150000000
0!
0$
0-
03
09
#1160000000
1!
1$
b00000011 +
1-
13
19
#1170000000
0!
0$
0-
03
09
#1180000000
1!
1$
b00000100 +
1-
13
19
#1190000000
0!
0$
0-
03
09
#1200000000
1!
1$
b00000101 +
1-
13
19
#1210000000
0!
0$
0-
03
09
#1220000000
1!
1$
b00000110 +
1-
13
19
#1230000000
0!
0$
0-
03
09
#1240000000
1!
1$
b00000111 +
1-
13
19
#1250000000
0!
0$
0-
03
09
#1260000000
1!
1$
b00001000 +
1-
13
19
#1270000000
0!
0$
0-
03
09
#1280000000
1!
1$
b00001001 +
1-
13
19
#1290000000
0!
0$
0-
03
09
#1300000000
1!
1$
b00001010 +
1-
13
19
#1310000000
0!
0$
0-
03
09
#1320000000
1!
1$
1(
b00000000 +
b00000101 ,
1-
11
13
19
#1330000000
0!
0$
0-
03
09
#1340000000
1!
1$
0(
1*
b00000001 +
1-
1/
01
b01000000 2
13
19
#1350000000
0!
0$
0-
03
09
#1360000000
1!
1"
1$
1%
b00000010 +
1-
13
14
17
19
1:
#1370000000
0!
0$
0-
03
09
#1380000000
1!
1$
b00000011 +
1-
13
19
b00000001 >
#1390000000
0!
0$
0-
03
09
#1400000000
1!
1$
b00000100 +
1-
13
19
b00000011 >
#1410000000
0!
0$
0-
03
09
#1420000000
1!
1$
b00000101 +
1-
13
19
b00000111 >
#1430000000
0!
0$
0-
03
09
#1440000000
1!
1$
b00000110 +
1-
13
19
b00001111 >
#1450000000
0!
0$
0-
03
09
#1460000000
1!
1$
b00000111 +
1-
13
19
b00011111 >
#1470000000
0!
0$
0-
03
09
#1480000000
1!
1$
b00001000 +
1-
13
19
b00111111 >
#1490000000
0!
0$
0-
03
09
#1500000000
1!
1$
b00001001 +
1-
13
19
b01111111 >
#1510000000
0!
0$
0-
03
09
#1520000000
1!
1$
b00001010 +
1-
13
19
b11111111 >
#1530000000
0!
0$
0-
03
09
#1540000000
1!
1$
1(
b00000000 +
b00000110 ,
1-
11
13
18
19
1;
#1550000000
0!
0$
0-
03
09
#1560000000
1!
1$
0(
0*
b00000001 +
1-
0/
01
b10000000 2
13
19
#1570000000
0!
0$
0-
03
09
#1580000000
1!
0"
1$
0%
b00000010 +
1-
13
04
07
19
0:
#1590000000
0!
0$
0-
03
09
#1600000000
1!
1$
b00000011 +
1-
13
19
b11111110 >
#1610000000
0!
0$
0-
03
09
#1620000000
1!
1$
b00000100 +
1-
13
19
b11111100 >
#1630000000
0!
0$
0-
03
09
#1640000000
1!
1$
b00000101 +
1-
13
19
b11111000 >
#1650000000
0!
0$
0-
03
09
#1660000000
1!
1$
b00000110 +
1-
13
19
b11110000 >
#1670000000
0!
0$
0-
03
09
#1680000000
1!
1$
b00000111 +
1-
13
19
b11100000 >
#1690000000
0!
0$
0-
03
09
#1700000000
1!
1$
b00001000 +
1-
13
19
b11000000 >
#1710000000
0!
0$
0-
03
09
#1720000000
1!
1$
b00001001 +
1-
13
19
b10000000 >
#1730000000
0!
0$
0-
03
09
#1740000000
1!
1$
b00001010 +
1-
13
19
b00000000 >
#1750000000
0!
0$
0-
03
09
#1760000000
1!
1$
1(
b00000000 +
b00000111 ,
1-
11
13
08
19
0;
#1770000000
0!
0$
0-
03
09
#1780000000
1!
1$
0(
1*
b00000001 +
1-
1/
01
b00000000 2
13
19
#1790000000
0!
0$
0-
03
09
#1800000000
1!
1"
1$
1%
b00000010 +
1-
13
14
17
19
1:
#1810000000
0!
0$
0-
03
09
#1820000000
1!
1$
b00000011 +
1-
13
19
b00000001 >
#1830000000
0!
0$
0-
03
09
#1840000000
1!
1$
b00000100 +
1-
13
19
b00000011 >
#1850000000
0!
0$
0-
03
09
#1860000000
1!
1$
b00000101 +
1-
13
19
b00000111 >
#1870000000
0!
0$
0-
03
09
#1880000000
1!
1$
b00000110 +
1-
13
19
b00001111 >
#1890000000
0!
0$
0-
03
09
#1900000000
1!
1$
b00000111 +
1-
13
19
b00011111 >
#1910000000
0!
0$
0-
03
09
#1920000000
1!
1$
b00001000 +
1-
13
19
b00111111 >
#1930000000
0!
0$
0-
03
09
#1940000000
1!
1$
b00001001 +
1-
13
19
b01111111 >
#1950000000
0!
0$
0-
03
09
#1960000000
1!
1$
b00001010 +
1-
13
19
b11111111 >
#1970000000
0!
0$
0-
03
09
#1980000000
1!
1$
1(
b00000000 +
b00001000 ,
1-
11
13
18
19
1;
#1990000000
0!
0$
0-
03
09
#2000000000
1!
1$
0*
b00000001 +
1-
0/
13
19
#2010000000
0!
0$
0-
03
09
#2020000000
1!
1$
b00000010 +
1-
13
19
#2030000000
0!
0$
0-
03
09
#2040000000
1!
1$
b00000011 +
1-
13
19
#2050000000
0!
0$
0-
03
09
#2060000000
1!
1$
b00000100 +
1-
13
19
#2070000000
0!
0$
0-
03
09
#2080000000
1!
1$
b00000101 +
1-
13
19
#2090000000
0!
0$
0-
03
09
#2100000000
1!
1$
b00000110 +
1-
13
19
#2110000000
0!
0$
0-
03
09
#2120000000
1!
1$
b00000111 +
1-
13
19
#2130000000
0!
0$
0-
03
09
#2140000000
1!
1$
b00001000 +
1-
13
19
#2150000000
0!
0$
0-
03
09
#2160000000
1!
1$
b00001001 +
1-
13
19
#2170000000
0!
0$
0-
03
09
#2180000000
1!
1$
b00001010 +
1-
13
19
#2190000000
0!
0$
0-
03
09
#2200000000
1!
1$
b00001011 +
1-
13
19
#2210000000
0!
0$
0-
03
09
#2220000000
1!
1$
b00000000 +
1-
13
19
#2230000000
0!
0$
0-
03
09
#2240000000
1!
0"
1$
0%
b00000001 +
1-
13
04
07
19
0:
#2250000000
0!
0$
0-
03
09
#2260000000
1!
1$
b00000010 +
1-
13
19
b11111110 >
#2270000000
0!
0$
0-
03
09
#2280000000
1!
1$
b00000011 +
1-
13
19
b11111100 >
#2290000000
0!
0$
0-
03
09
#2300000000
1!
1$
b00000100 +
1-
13
19
b11111000 >
#2310000000
0!
0$
0-
03
09
#2320000000
1!
1$
b00000101 +
1-
13
19
b11110000 >
#2330000000
0!
0$
0-
03
09
#2340000000
1!
1$
b00000110 +
1-
13
19
b11100000 >
#2350000000
0!
0$
0-
03
09
#2360000000
1!
1$
b00000111 +
1-
13
19
b11000000 >
#2370000000
0!
0$
0-
03
09
#2380000000
1!
1$
b00001000 +
1-
13
19
b10000000 >
#2390000000
0!
0$
0-
03
09
#2400000000
1!
1$
b00001001 +
1-
13
19
b00000000 >
#2410000000
0!
0$
0-
03
09
#2420000000
1!
1$
b00000000 +
b00000000 ,
1-
13
08
19
0;
#2430000000
0!
0$
0-
03
09
#2440000000
1!
1$
0(
b00000001 +
1-
01
13
19
#2450000000
0!
0$
0-
03
09
#2460000000
1!
1$
b00000010 +
1-
13
19
#2470000000
0!
0$
0-
03
09
#2480000000
1!
1$
b00000011 +
1-
13
19
#2490000000
0!
0$
0-
03
09
#2500000000
1!
1$
b00000100 +
1-
13
19
#2510000000
0!
0$
0-
03
09
#2520000000
1!
1$
b00000101 +
1-
13
19
#2530000000
0!
0$
0-
03
09
#2540000000
1!
1$
b00000110 +
1-
13
19
#2550000000
0!
0$
0-
03
09
#2560000000
1!
1$
b00000111 +
1-
13
19
#2570000000
0!
0$
0-
03
09
#2580000000
1!
1$
b00001000 +
1-
13
19
#2590000000
0!
0$
0-
03
09
#2600000000
1!
1$
b00001001 +
1-
13
19
#2610000000
0!
0$
0-
03
09
#2620000000
1!
1$
b00001010 +
1-
13
19
#2630000000
0!
0$
0-
03
09
#2640000000
1!
1$
1(
b00000000 +
b00000001 ,
1-
11
13
19
#2650000000
0!
0$
0-
03
09
#2660000000
1!
1$
0(
b00000001 +
1-
01
13
19
#2670000000
0!
0$
0-
03
09
#2680000000
1!
1$
b00000010 +
1-
13
19
#2690000000
0!
0$
0-
03
09
#2700000000
1!
1$
b00000011 +
1-
13
19
#2710000000
0!
0$
0-
03
09
#2720000000
1!
1$
b00000100 +
1-
13
19
#2730000000
0!
0$
0-
03
09
#2740000000
1!
1$
b00000101 +
1-
13
19
#2750000000
0!
0$
0-
03
09
#2760000000
1!
1$
b00000110 +
1-
13
19
#2770000000
0!
0$
0-
03
09
#2780000000
1!
1$
b00000111 +
1-
13
19
#2790000000
0!
0$
0-
03
09
#2800000000
1!
1$
b00001000 +
1-
13
19
#2810000000
0!
0$
0-
03
09
#2820000000
1!
1$
b00001001 +
1-
13
19
#2830000000
0!
0$
0-
03
09
#2840000000
1!
1$
b00001010 +
1-
13
19
#2850000000
0!
0$
0-
03
09
#2860000000
1!
1$
1(
b00000000 +
b00000010 ,
1-
11
13
19
#2870000000
0!
0$
0-
03
09
#2880000000
1!
1$
0(
b00000001 +
1-
01
13
19
#2890000000
0!
0$
0-
03
09
#2900000000
1!
1$
b00000010 +
1-
13
19
#2910000000
0!
0$
0-
03
09
#2920000000
1!
1$
b00000011 +
1-
13
19
#2930000000
0!
0$
0-
03
09
#2940000000
1!
1$
b00000100 +
1-
13
19
#2950000000
0!
0$
0-
03
09
#2960000000
1!
1$
b00000101 +
1-
13
19
#2970000000
0!
0$
0-
03
09
#2980000000
1!
1$
b00000110 +
1-
13
19
#2990000000
0!
0$
0-
03
09
#3000000000
1!
1$
b00000111 +
1-
13
19
#3010000000
0!
0$
0-
03
09
#3020000000
1!
1$
b00001000 +
1-
13
19
#3030000000
0!
0$
0-
03
09
#3040000000
1!
1$
b00001001 +
1-
13
19
#3050000000
0!
0$
0-
03
09
#3060000000
1!
1$
b00001010 +
1-
13
19
#3070000000
0!
0$
0-
03
09
#3080000000
1!
1$
1(
b00000000 +
b00000011 ,
1-
11
13
19
#3090000000
0!
0$
0-
03
09
#3100000000
1!
1$
0(
b00000001 +
1-
01
13
19
#3110000000
0!
0$
0-
03
09
#3120000000
1!
1$
b00000010 +
1-
13
19
#3130000000
0!
0$
0-
03
09
#3140000000
1!
1$
b00000011 +
1-
13
19
#3150000000
0!
0$
0-
03
09
#3160000000
1!
1$
b00000100 +
1-
13
19
#3170000000
0!
0$
0-
03
09
#3180000000
1!
1$
b00000101 +
1-
13
19
#3190000000
0!
0$
0-
03
09
#3200000000
1!
1$
b00000110 +
1-
13
19
#3210000000
0!
0$
0-
03
09
#3220000000
1!
1$
b00000111 +
1-
13
19
#3230000000
0!
0$
0-
03
09
#3240000000
1!
1$
b00001000 +
1-
13
19
#3250000000
0!
0$
0-
03
09
#3260000000
1!
1$
b00001001 +
1-
13
19
#3270000000
0!
0$
0-
03
09
#3280000000
1!
1$
b00001010 +
1-
13
19
#3290000000
0!
0$
0-
03
09
#3300000000
1!
1$
1(
b00000000 +
b00000100 ,
1-
11
13
19
#3310000000
0!
0$
0-
03
09
#3320000000
1!
1$
0(
b00000001 +
1-
01
13
19
#3330000000
0!
0$
0-
03
09
#3340000000
1!
1$
b00000010 +
1-
13
19
#3350000000
0!
0$
0-
03
09
#3360000000
1!
1$
b00000011 +
1-
13
19
#3370000000
0!
0$
0-
03
09
#3380000000
1!
1$
b00000100 +
1-
13
19
#3390000000
0!
0$
0-
03
09
#3400000000
1!
1$
b00000101 +
1-
13
19
#3410000000
0!
0$
0-
03
09
#3420000000
1!
1$
b00000110 +
1-
13
19
#3430000000
0!
0$
0-
03
09
#3440000000
1!
1$
b00000111 +
1-
13
19
#3450000000
0!
0$
0-
03
09
#3460000000
1!
1$
b00001000 +
1-
13
19
#3470000000
0!
0$
0-
03
09
#3480000000
1!
1$
b00001001 +
1-
13
19
#3490000000
0!
0$
0-
03
09
#3500000000
1!
1$
b00001010 +
1-
13
19
#3510000000
0!
0$
0-
03
09
#3520000000
1!
1$
1(
b00000000 +
b00000101 ,
1-
11
13
19
#3530000000
0!
0$
0-
03
09
#3540000000
1!
1$
0(
b00000001 +
1-
01
13
19
#3550000000
0!
0$
0-
03
09
#3560000000
1!
1$
b00000010 +
1-
13
19
#3570000000
0!
0$
0-
03
09
#3580000000
1!
1$
b00000011 +
1-
13
19
#3590000000
0!
0$
0-
03
09
#3600000000
1!
1$
b00000100 +
1-
13
19
#3610000000
0!
0$
0-
03
09
#3620000000
1!
1$
b00000101 +
1-
13
19
#3630000000
0!
0$
0-
03
09
#3640000000
1!
1$
b00000110 +
1-
13
19
#3650000000
0!
0$
0-
03
09
#3660000000
1!
1$
b00000111 +
1-
13
19
#3670000000
0!
0$
0-
03
09
#3680000000
1!
1$
b00001000 +
1-
13
19
#3690000000
0!
0$
0-
03
09
#3700000000
1!
1$
b00001001 +
1-
13
19
#3710000000
0!
0$
0-
03
09
#3720000000
1!
1$
b00001010 +
1-
13
19
#3730000000
0!
0$
0-
03
09
#3740000000
1!
1$
1(
b00000000 +
b00000110 ,
1-
11
13
19
#3750000000
0!
0$
0-
03
09
#3760000000
1!
1$
0(
b00000001 +
1-
01
13
19
#3770000000
0!
0$
0-
03
09
#3780000000
1!
1$
b00000010 +
1-
13
19
#3790000000
0!
0$
0-
03
09
#3800000000
1!
1$
b00000011 +
1-
13
19
#3810000000
0!
0$
0-
03
09
#3820000000
1!
1$
b00000100 +
1-
13
19
#3830000000
0!
0$
0-
03
09
#3840000000
1!
1$
b00000101 +
1-
13
19
#3850000000
0!
0$
0-
03
09
#3860000000
1!
1$
b00000110 +
1-
13
19
#3870000000
0!
0$
0-
03
09
#3880000000
1!
1$
b00000111 +
1-
13
19
#3890000000
0!
0$
0-
03
09
#3900000000
1!
1$
b00001000 +
1-
13
19
#3910000000
0!
0$
0-
03
09
#3920000000
1!
1$
b00001001 +
1-
13
19
#3930000000
0!
0$
0-
03
09
#3940000000
1!
1$
b00001010 +
1-
13
19
#3950000000
0!
0$
0-
03
09
#3960000000
1!
1$
1(
b00000000 +
b00000111 ,
1-
11
13
19
#3970000000
0!
0$
0-
03
09
#3980000000
1!
1$
0(
b00000001 +
1-
01
13
19
#3990000000
0!
0$
0-
03
09
#4000000000
1!
1$
b00000010 +
1-
13
19
#4010000000
0!
0$
0-
03
09
#4020000000
1!
1$
b00000011 +
1-
13
19
#4030000000
0!
0$
0-
03
09
#4040000000
1!
1$
b00000100 +
1-
13
19
#4050000000
0!
0$
0-
03
09
#4060000000
1!
1$
b00000101 +
1-
13
19
#4070000000
0!
0$
0-
03
09
#4080000000
1!
1$
b00000110 +
1-
13
19
#4090000000
0!
0$
0-
03
09
#4100000000
1!
1$
b00000111 +
1-
13
19
#4110000000
0!
0$
0-
03
09
#4120000000
1!
1$
b00001000 +
1-
13
19
#4130000000
0!
0$
0-
03
09
#4140000000
1!
1$
b00001001 +
1-
13
19
#4150000000
0!
0$
0-
03
09
#4160000000
1!
1$
b00001010 +
1-
13
19
#4170000000
0!
0$
0-
03
09
#4180000000
1!
1$
1(
b00000000 +
b00001000 ,
1-
11
13
19
#4190000000
0!
0$
0-
03
09
#4200000000
1!
1$
b00000001 +
1-
13
19
#4210000000
0!
0$
0-
03
09
#4220000000
1!
1"
1$
1%
b00000010 +
1-
13
14
17
19
1:
#4230000000
0!
0$
0-
03
09
#4240000000
1!
1$
b00000011 +
1-
13
19
b00000001 >
#4250000000
0!
0$
0-
03
09
#4260000000
1!
1$
b00000100 +
1-
13
19
b00000011 >
#4270000000
0!
0$
0-
03
09
#4280000000
1!
1$
b00000101 +
1-
13
19
b00000111 >
#4290000000
0!
0$
0-
03
09
#4300000000
1!
1$
b00000110 +
1-
13
19
b00001111 >
#4310000000
0!
0$
0-
03
09
#4320000000
1!
1$
b00000111 +
1-
13
19
b00011111 >
#4330000000
0!
0$
0-
03
09
#4340000000
1!
1$
b00001000 +
1-
13
19
b00111111 >
#4350000000
0!
0$
0-
03
09
#4360000000
1!
1$
b00001001 +
1-
13
19
b01111111 >
#4370000000
0!
0$
0-
03
09
#4380000000
1!
1$
b00001010 +
1-
13
19
b11111111 >
#4390000000
0!
0$
0-
03
09
#4400000000
1!
1$
b00001011 +
1-
13
18
19
1;
#4410000000
0!
0$
0-
03
09
#4420000000
1!
1$
b00000000 +
1-
13
19
#4430000000
0!
0$
0-
03
09
#4440000000
1!
0"
1$
0%
b00000001 +
1-
13
04
07
19
0:
#4450000000
0!
0$
0-
03
09
#4460000000
1!
1$
b00000010 +
1-
13
19
b11111110 >
#4470000000
0!
0$
0-
03
09
#4480000000
1!
1$
b00000011 +
1-
13
19
b11111100 >
#4490000000
0!
0$
0-
03
09
#4500000000
1!
1$
b00000100 +
1-
13
19
b11111000 >
#4510000000
0!
0$
0-
03
09
#4520000000
1!
1$
b00000101 +
1-
13
19
b11110000 >
#4530000000
0!
0$
0-
03
09
#4540000000
1!
1$
b00000110 +
1-
13
19
b11100000 >
#4550000000
0!
0$
0-
03
09
#4560000000
1!
1$
b00000111 +
1-
13
19
b11000000 >
#4570000000
0!
0$
0-
03
09
#4580000000
1!
1$
b00001000 +
1-
13
19
b10000000 >
#4590000000
0!
0$
0-
03
09
#4600000000
1!
1$
b00001001 +
1-
13
19
b00000000 >
#4610000000
0!
0$
0-
03
09
#4620000000
1!
1$
b00000000 +
b00000000 ,
1-
13
08
19
0;
#4630000000
0!
0$
0-
03
09
#4640000000
1!
1$
0(
b00000001 +
1-
01
13
19
#4650000000
0!
0$
0-
03
09
#4660000000
1!
1$
b00000010 +
1-
13
19
#4670000000
0!
0$
0-
03
09
#4680000000
1!
1$
b00000011 +
1-
13
19
#4690000000
0!
0$
0-
03
09
#4700000000
1!
1$
b00000100 +
1-
13
19
#4710000000
0!
0$
0-
03
09
#4720000000
1!
1$
b00000101 +
1-
13
19
#4730000000
0!
0$
0-
03
09
#4740000000
1!
1$
b00000110 +
1-
13
19
#4750000000
0!
0$
0-
03
09
#4760000000
1!
1$
b00000111 +
1-
13
19
#4770000000
0!
0$
0-
03
09
#4780000000
1!
1$
b00001000 +
1-
13
19
#4790000000
0!
0$
0-
03
09
#4800000000
1!
1$
b00001001 +
1-
13
19
#4810000000
0!
0$
0-
03
09
#4820000000
1!
1$
b00001010 +
1-
13
19
#4830000000
0!
0$
0-
03
09
#4840000000
1!
1$
1(
b00000000 +
b00000001 ,
1-
11
13
19
#4850000000
0!
0$
0-
03
09
#4860000000
1!
1$
0(
b00000001 +
1-
01
13
19
#4870000000
0!
0$
0-
03
09
#4880000000
1!
1$
b00000010 +
1-
13
19
#4890000000
0!
0$
0-
03
09
#4900000000
1!
1$
b00000011 +
1-
13
19
#4910000000
0!
0$
0-
03
09
#4920000000
1!
1$
b00000100 +
1-
13
19
