uart/shift_register.vhd
library ieee;
use ieee.std_logic_1164.all;
use ieee.numeric_std.all;

entity shift_register is
  port (
      clk: in std_logic;
      shift_input: in std_logic;
      shift_output: out std_logic;
      reset: in std_logic := '0';
      enable: in std_logic := '0';
      buf: buffer std_logic_vector(7 downto 0) := "10100101"
  );
end entity shift_register;

architecture rtl of shift_register is

begin
    process(clk)
      begin
        if rising_edge(clk) then
          if reset = '1' then
            buf <= (others => '0');
            shift_output <= '0';
          elsif enable = '1' then 
            buf <= buf(6 downto 0) & shift_input;
            shift_output <= buf(7);
          end if;
        end if;

      end process;

end architecture rtl;

uart/uart_receiver.vhd
library ieee;
use ieee.std_logic_1164.all;
use ieee.numeric_std.all;

entity uart_receiver is
  port (
      clk: in std_logic;
      serial_in: in std_logic;
      shift_register_reset: buffer std_logic := '0';
      shift_register_enable: buffer std_logic := '0';
      shift_register_input: buffer std_logic;
      shift_register_output: buffer std_logic := '0';
      done: out std_logic := '0'
  );
end entity uart_receiver;

architecture rtl of uart_receiver is

  type state_t is (IDLE, START, DATA, STOP);
  signal state: state_t := IDLE;
  signal time_counter: unsigned(7 downto 0) := (others => '0');
  signal bits_sent_counter: unsigned(7 downto 0) := (others => '0');

begin

  shift_register : entity work.shift_register
    port map (
      clk => clk,
      shift_input => serial_in, 
      shift_output => shift_register_output, 
      reset => shift_register_reset,
      enable => shift_register_enable
    );

    process(clk)
      begin

        if rising_edge(clk) then
        if state = IDLE then

          done <= '0';
          if serial_in = '0' then
            state <= START;
            shift_register_reset <= '1';
            time_counter <= (others => '0');
          end if;

        elsif state = START then

          if time_counter = 12 then 
            time_counter <= (others => '0');
            state <= DATA;
          else 
            shift_register_reset <= '0';
            time_counter <= time_counter + 1;
          end if;

        elsif state = DATA then

            time_counter <= time_counter +1;

            if bits_sent_counter < 8 then 
              if time_counter = 0 then
                shift_register_enable <= '1';
                shift_register_input <= serial_in;

              elsif time_counter >= 10 then
                bits_sent_counter <= bits_sent_counter + 1;
                time_counter <= (others => '0');
              else
                shift_register_enable <= '0';
              end if;

            else
                state <= STOP;
                time_counter <= (others => '0');
            end if;

        elsif state = STOP then

          if time_counter = 5 then 
            time_counter <= (others => '0');
            state <= IDLE;
            done <= '1';
          else 
            time_counter <= time_counter + 1;
          end if;
        end if;
        -- so i have 2 states
        -- State 1 -> wait for a low on the wire then sync clock and switch state
        -- State 2 -> read current bit into the shift register until you got 8 and switch an "im done bit" and go back to the state 1

      end if;

    end process;
end architecture rtl;

uart/uart_sender.vhd
library ieee;
use ieee.std_logic_1164.all;
use ieee.numeric_std.all;


entity uart_sender is
  port (
      clk: in std_logic;
      serial_out: out std_logic := '1';
      send: in std_logic;
      shift_register_reset: buffer std_logic := '0';
      shift_register_enable: buffer std_logic := '0';
      shift_register_input: buffer std_logic := '0';
      shift_register_output: buffer std_logic
      
  );
end entity uart_sender;

architecture rtl of uart_sender is

  type state_t is (IDLE, START, DATA, STOP);
  signal state: state_t := IDLE;
  signal time_counter: unsigned(7 downto 0) := (others => '0');
  signal bits_sent_counter: unsigned(7 downto 0) := (others => '0');
  -- State 1 - make it possible to read values into you - when you get the signal to send something switch into state 2
  -- State 2 - send over the bits one by one and go back to state 1
begin

      -- clk: in std_logic;
      -- shift_input: in std_logic;
      -- shift_output: out std_logic;
      -- reset: in std_logic := '0';
      -- enable: in std_logic := '0';

  shift_register : entity work.shift_register
    port map (
      clk => clk,
      shift_input => shift_register_input, 
      shift_output => shift_register_output, 
      reset => shift_register_reset,
      enable => shift_register_enable
    );

    process(clk)
      begin
        if rising_edge(clk) then
          if state = IDLE then
            serial_out <= '1';
            if send = '1' then 
              state <= START;
              time_counter <= (others => '0');
            end if;

          elsif state = START then
            if time_counter = 0 then
              serial_out <= '0';
              time_counter <= time_counter +1;
            elsif time_counter >= 9 then  
              state <= DATA;
              time_counter <= (others => '0');
              bits_sent_counter <= (others => '0');
              shift_register_enable <= '1';
            else 
              time_counter <= time_counter +1;
            end if;


          elsif state = DATA then 

            time_counter <= time_counter +1;

            if bits_sent_counter < 8 then 

              if time_counter = 0 then
                shift_register_enable <= '0';
              elsif time_counter >= 10 then
                -- bit sent here 
                bits_sent_counter <= bits_sent_counter + 1;
                shift_register_enable <= '1';
                time_counter <= (others => '0');
              else
                serial_out <= shift_register_output;
              end if;

            else
                state <= STOP;
            end if;



          elsif state = STOP then 
            serial_out <= '1';
            time_counter <= time_counter +1;
            if time_counter >= 10 then 
              state <= IDLE;
            end if;
          end if ;
          

        end if;

      end process;

end architecture rtl;

uart/tb_uart.vhd
library ieee;
use ieee.std_logic_1164.all;
use ieee.numeric_std.all;

entity tb_uart is
end entity tb_uart;

architecture sim of tb_uart is

      signal clk:  std_logic := '0';
      signal serial: std_logic;
      signal done: std_logic := '0';
      signal send: std_logic := '0';

begin

  sender : entity work.uart_sender
    port map (
      clk => clk,
      serial_out => serial,
      send => send
    );
    
  receiver : entity work.uart_receiver
    port map (
      clk => clk,
      serial_in => serial,
      done => done
    );

  stimulus : process
  begin
    wait for 10 ns;

    send <= '1';
    wait for 10 ns;
    clk <= '1';
    wait for 10 ns;
    clk <= '0';
    wait for 10 ns;
    send <= '0';

    while done = '0' loop
      clk <= '1';
      wait for 10 ns;
      clk <= '0';
      wait for 10 ns;
    end loop;


    wait;

  end process;

end architecture sim;

uart/tb_uart.vcd
$date
  Tue Aug 25 19:26:47 2026
$end
$version
  GHDL v0
$end
$timescale
  1 fs
$end
$scope module standard $end
$upscope $end
$scope module textio $end
$upscope $end
$scope module std_logic_1164 $end
$upscope $end
$scope module numeric_std $end
$upscope $end
$scope module tb_uart $end
$var reg 1 ! clk $end
$var reg 1 " serial $end
$var reg 1 # done $end
$var reg 1 $ send $end
$scope module sender $end
$var reg 1 % clk $end
$var reg 1 & serial_out $end
$var reg 1 ' send $end
$var reg 1 ( shift_register_reset $end
$var reg 1 ) shift_register_enable $end
$var reg 1 * shift_register_input $end
$var reg 1 + shift_register_output $end
$comment state is not handled $end
$var reg 8 , time_counter[7:0] $end
$var reg 8 - bits_sent_counter[7:0] $end
$scope module shift_register $end
$var reg 1 . clk $end
$var reg 1 / shift_input $end
$var reg 1 0 shift_output $end
$var reg 1 1 reset $end
$var reg 1 2 enable $end
$var reg 8 3 buf[7:0] $end
$upscope $end
$upscope $end
$scope module receiver $end
$var reg 1 4 clk $end
$var reg 1 5 serial_in $end
$var reg 1 6 shift_register_reset $end
$var reg 1 7 shift_register_enable $end
$var reg 1 8 shift_register_input $end
$var reg 1 9 shift_register_output $end
$var reg 1 : done $end
$comment state is not handled $end
$var reg 8 ; time_counter[7:0] $end
$var reg 8 < bits_sent_counter[7:0] $end
$scope module shift_register $end
$var reg 1 = clk $end
$var reg 1 > shift_input $end
$var reg 1 ? shift_output $end
$var reg 1 @ reset $end
$var reg 1 A enable $end
$var reg 8 B buf[7:0] $end
$upscope $end
$upscope $end
$upscope $end
$enddefinitions $end
#0
0!
1"
0#
0$
0%
1&
0'
0(
0)
0*
U+
b00000000 ,
b00000000 -
0.
0/
U0
01
02
b10100101 3
04
15
06
07
U8
U9
0:
b00000000 ;
b00000000 <
0=
1>
U?
0@
0A
b10100101 B
#10000000
1$
1'
#20000000
1!
1%
1.
14
1=
#30000000
0!
0%
0.
04
0=
#40000000
1!
0"
0$
1%
0&
0'
b00000001 ,
1.
14
05
1=
0>
#50000000
0!
0%
0.
04
0=
#60000000
1!
1%
b00000010 ,
1.
14
16
1=
1@
#70000000
0!
0%
0.
04
0=
#80000000
1!
1%
b00000011 ,
1.
14
06
09
b00000001 ;
1=
0?
0@
b00000000 B
#90000000
0!
0%
0.
04
0=
#100000000
1!
1%
b00000100 ,
1.
14
b00000010 ;
1=
#110000000
0!
0%
0.
04
0=
#120000000
1!
1%
b00000101 ,
1.
14
b00000011 ;
1=
#130000000
0!
0%
0.
04
0=
#140000000
1!
1%
b00000110 ,
1.
14
b00000100 ;
1=
#150000000
0!
0%
0.
04
0=
#160000000
1!
1%
b00000111 ,
1.
14
b00000101 ;
1=
#170000000
0!
0%
0.
04
0=
#180000000
1!
1%
b00001000 ,
1.
14
b00000110 ;
1=
#190000000
0!
0%
0.
04
0=
#200000000
1!
1%
b00001001 ,
1.
14
b00000111 ;
1=
#210000000
0!
0%
0.
04
0=
#220000000
1!
1%
1)
b00000000 ,
1.
12
14
b00001000 ;
1=
#230000000
0!
0%
0.
04
0=
#240000000
1!
1%
0)
1+
b00000001 ,
1.
10
02
b01001010 3
14
b00001001 ;
1=
#250000000
0!
0%
0.
04
0=
#260000000
1!
1"
1%
1&
b00000010 ,
1.
14
15
b00001010 ;
1=
1>
#270000000
0!
0%
0.
04
0=
#280000000
1!
1%
b00000011 ,
1.
14
b00001011 ;
1=
#290000000
0!
0%
0.
04
0=
#300000000
1!
1%
b00000100 ,
1.
14
b00001100 ;
1=
#310000000
0!
0%
0.
04
0=
#320000000
1!
1%
b00000101 ,
1.
14
b00000000 ;
1=
#330000000
0!
0%
0.
04
0=
#340000000
1!
1%
b00000110 ,
1.
14
17
18
b00000001 ;
1=
1A
#350000000
0!
0%
0.
04
0=
#360000000
1!
1%
b00000111 ,
1.
14
07
b00000010 ;
1=
0A
b00000001 B
#370000000
0!
0%
0.
04
0=
#380000000
1!
1%
b00001000 ,
1.
14
b00000011 ;
1=
#390000000
0!
0%
0.
04
0=
#400000000
1!
1%
b00001001 ,
1.
14
b00000100 ;
1=
#410000000
0!
0%
0.
04
0=
#420000000
1!
1%
b00001010 ,
1.
14
b00000101 ;
1=
#430000000
0!
0%
0.
04
0=
#440000000
1!
1%
1)
b00000000 ,
b00000001 -
1.
12
14
b00000110 ;
1=
#450000000
0!
0%
0.
04
0=
#460000000
1!
1%
0)
0+
b00000001 ,
1.
00
02
b10010100 3
14
b00000111 ;
1=
#470000000
0!
0%
0.
04
0=
#480000000
1!
0"
1%
0&
b00000010 ,
1.
14
05
b00001000 ;
1=
0>
#490000000
0!
0%
0.
04
0=
#500000000
1!
1%
b00000011 ,
1.
14
b00001001 ;
1=
#510000000
0!
0%
0.
04
0=
#520000000
1!
1%
b00000100 ,
1.
14
b00001010 ;
1=
#530000000
0!
0%
0.
04
0=
#540000000
1!
1%
b00000101 ,
1.
14
b00000000 ;
b00000001 <
1=
#550000000
0!
0%
0.
04
0=
#560000000
1!
1%
b00000110 ,
1.
14
17
08
b00000001 ;
1=
1A
#570000000
0!
0%
0.
04
0=
#580000000
1!
1%
b00000111 ,
1.
14
07
b00000010 ;
1=
0A
b00000010 B
#590000000
0!
0%
0.
04
0=
#600000000
1!
1%
b00001000 ,
1.
14
b00000011 ;
1=
#610000000
0!
0%
0.
04
0=
#620000000
1!
1%
b00001001 ,
1.
14
b00000100 ;
1=
#630000000
0!
0%
0.
04
0=
#640000000
1!
1%
b00001010 ,
1.
14
b00000101 ;
1=
#650000000
0!
0%
0.
04
0=
#660000000
1!
1%
1)
b00000000 ,
b00000010 -
1.
12
14
b00000110 ;
1=
#670000000
0!
0%
0.
04
0=
#680000000
1!
1%
0)
1+
b00000001 ,
1.
10
02
b00101000 3
14
b00000111 ;
1=
#690000000
0!
0%
0.
04
0=
#700000000
1!
1"
1%
1&
b00000010 ,
1.
14
15
b00001000 ;
1=
1>
#710000000
0!
0%
0.
04
0=
#720000000
1!
1%
b00000011 ,
1.
14
b00001001 ;
1=
#730000000
0!
0%
0.
04
0=
#740000000
1!
1%
b00000100 ,
1.
14
b00001010 ;
1=
#750000000
0!
0%
0.
04
0=
#760000000
1!
1%
b00000101 ,
1.
14
b00000000 ;
b00000010 <
1=
#770000000
0!
0%
0.
04
0=
#780000000
1!
1%
b00000110 ,
1.
14
17
18
b00000001 ;
1=
1A
#790000000
0!
0%
0.
04
0=
#800000000
1!
1%
b00000111 ,
1.
14
07
b00000010 ;
1=
0A
b00000101 B
#810000000
0!
0%
0.
04
0=
#820000000
1!
1%
b00001000 ,
1.
14
b00000011 ;
1=
#830000000
0!
0%
0.
04
0=
#840000000
1!
1%
b00001001 ,
1.
14
b00000100 ;
1=
#850000000
0!
0%
0.
04
0=
#860000000
1!
1%
b00001010 ,
1.
14
b00000101 ;
1=
#870000000
0!
0%
0.
04
0=
#880000000
1!
1%
1)
b00000000 ,
b00000011 -
1.
12
14
b00000110 ;
1=
#890000000
0!
0%
0.
04
0=
#900000000
1!
1%
0)
0+
b00000001 ,
1.
00
02
b01010000 3
14
b00000111 ;
1=
#910000000
0!
0%
0.
04
0=
#920000000
1!
0"
1%
0&
b00000010 ,
1.
14
05
b00001000 ;
1=
0>
#930000000
0!
0%
0.
04
0=
#940000000
1!
1%
b00000011 ,
1.
14
b00001001 ;
1=
#950000000
0!
0%
0.
04
0=
#960000000
1!
1%
b00000100 ,
1.
14
b00001010 ;
1=
#970000000
0!
0%
0.
04
0=
#980000000
1!
1%
b00000101 ,
1.
14
b00000000 ;
b00000011 <
1=
#990000000
0!
0%
0.
04
0=
#1000000000
1!
1%
b00000110 ,
1.
14
17
08
b00000001 ;
1=
1A
#1010000000
0!
0%
0.
04
0=
#1020000000
1!
1%
b00000111 ,
1.
14
07
b00000010 ;
1=
0A
b00001010 B
#1030000000
0!
0%
0.
04
0=
#1040000000
1!
1%
b00001000 ,
1.
14
b00000011 ;
1=
#1050000000
0!
0%
0.
04
0=
#1060000000
1!
1%
b00001001 ,
1.
14
b00000100 ;
1=
#1070000000
0!
0%
0.
04
0=
#1080000000
1!
1%
b00001010 ,
1.
14
b00000101 ;
1=
#1090000000
0!
0%
0.
04
0=
#1100000000
1!
1%
1)
b00000000 ,
b00000100 -
1.
12
14
b00000110 ;
1=
#1110000000
0!
0%
0.
04
0=
#1120000000
1!
1%
0)
b00000001 ,
1.
02
b10100000 3
14
b00000111 ;
1=
#1130000000
0!
0%
0.
04
0=
#1140000000
1!
1%
b00000010 ,
1.
14
b00001000 ;
1=
#1150000000
0!
0%
0.
04
0=
#1160000000
1!
1%
b00000011 ,
1.
14
b00001001 ;
1=
#1170000000
0!
0%
0.
04
0=
#1180000000
1!
1%
b00000100 ,
1.
14
b00001010 ;
1=
#1190000000
0!
0%
0.
04
0=
#1200000000
1!
1%
b00000101 ,
1.
14
b00000000 ;
b00000100 <
1=
#1210000000
0!
0%
0.
04
0=
#1220000000
1!
1%
b00000110 ,
1.
14
17
b00000001 ;
1=
1A
#1230000000
0!
0%
0.
04
0=
#1240000000
1!
1%
b00000111 ,
1.
14
07
b00000010 ;
1=
0A
b00010100 B
#1250000000
0!
0%
0.
04
0=
#1260000000
1!
1%
b00001000 ,
1.
14
b00000011 ;
1=
#1270000000
0!
0%
0.
04
0=
#1280000000
1!
1%
b00001001 ,
1.
14
b00000100 ;
1=
#1290000000
0!
0%
0.
04
0=
#1300000000
1!
1%
b00001010 ,
1.
14
b00000101 ;
1=
#1310000000
0!
0%
0.
04
0=
#1320000000
1!
1%
1)
b00000000 ,
b00000101 -
1.
12
14
b00000110 ;
1=
#1330000000
0!
0%
0.
04
0=
#1340000000
1!
1%
0)
1+
b00000001 ,
1.
10
02
b01000000 3
14
b00000111 ;
1=
#1350000000
0!
0%
0.
04
0=
#1360000000
1!
1"
1%
1&
b00000010 ,
1.
14
15
b00001000 ;
1=
1>
#1370000000
0!
0%
0.
04
0=
#1380000000
1!
1%
b00000011 ,
1.
14
b00001001 ;
1=
#1390000000
0!
0%
0.
04
0=
#1400000000
1!
1%
b00000100 ,
1.
14
b00001010 ;
1=
#1410000000
0!
0%
0.
04
0=
#1420000000
1!
1%
b00000101 ,
1.
14
b00000000 ;
b00000101 <
1=
#1430000000
0!
0%
0.
04
0=
#1440000000
1!
1%
b00000110 ,
1.
14
17
18
b00000001 ;
1=
1A
#1450000000
0!
0%
0.
04
0=
#1460000000
1!
1%
b00000111 ,
1.
14
07
b00000010 ;
1=
0A
b00101001 B
#1470000000
0!
0%
0.
04
0=
#1480000000
1!
1%
b00001000 ,
1.
14
b00000011 ;
1=
#1490000000
0!
0%
0.
04
0=
#1500000000
1!
1%
b00001001 ,
1.
14
b00000100 ;
1=
#1510000000
0!
0%
0.
04
0=
#1520000000
1!
1%
b00001010 ,
1.
14
b00000101 ;
1=
#1530000000
0!
0%
0.
04
0=
#1540000000
1!
1%
1)
b00000000 ,
b00000110 -
1.
12
14
b00000110 ;
1=
#1550000000
0!
0%
0.
04
0=
#1560000000
1!
1%
0)
0+
b00000001 ,
1.
00
02
b10000000 3
14
b00000111 ;
1=
#1570000000
0!
0%
0.
04
0=
#1580000000
1!
0"
1%
0&
b00000010 ,
1.
14
05
b00001000 ;
1=
0>
#1590000000
0!
0%
0.
04
0=
#1600000000
1!
1%
b00000011 ,
1.
14
b00001001 ;
1=
#1610000000
0!
0%
0.
04
0=
#1620000000
1!
1%
b00000100 ,
1.
14
b00001010 ;
1=
#1630000000
0!
0%
0.
04
0=
#1640000000
1!
1%
b00000101 ,
1.
14
b00000000 ;
b00000110 <
1=
#1650000000
0!
0%
0.
04
0=
#1660000000
1!
1%
b00000110 ,
1.
14
17
08
b00000001 ;
1=
1A
#1670000000
0!
0%
0.
04
0=
#1680000000
1!
1%
b00000111 ,
1.
14
07
b00000010 ;
1=
0A
b01010010 B
#1690000000
0!
0%
0.
04
0=
#1700000000
1!
1%
b00001000 ,
1.
14
b00000011 ;
1=
#1710000000
0!
0%
0.
04
0=
#1720000000
1!
1%
b00001001 ,
1.
14
b00000100 ;
1=
#1730000000
0!
0%
0.
04
0=
#1740000000
1!
1%
b00001010 ,
1.
14
b00000101 ;
1=
#1750000000
0!
0%
0.
04
0=
#1760000000
1!
1%
1)
b00000000 ,
b00000111 -
1.
12
14
b00000110 ;
1=
#1770000000
0!
0%
0.
04
0=
#1780000000
1!
1%
0)
1+
b00000001 ,
1.
10
02
b00000000 3
14
b00000111 ;
1=
#1790000000
0!
0%
0.
04
0=
#1800000000
1!
1"
1%
1&
b00000010 ,
1.
14
15
b00001000 ;
1=
1>
#1810000000
0!
0%
0.
04
0=
#1820000000
1!
1%
b00000011 ,
1.
14
b00001001 ;
1=
#1830000000
0!
0%
0.
04
0=
#1840000000
1!
1%
b00000100 ,
1.
14
b00001010 ;
1=
#1850000000
0!
0%
0.
04
0=
#1860000000
1!
1%
b00000101 ,
1.
14
b00000000 ;
b00000111 <
1=
#1870000000
0!
0%
0.
04
0=
#1880000000
1!
1%
b00000110 ,
1.
14
17
18
b00000001 ;
1=
1A
#1890000000
0!
0%
0.
04
0=
#1900000000
1!
1%
b00000111 ,
1.
14
07
b00000010 ;
1=
0A
b10100101 B
#1910000000
0!
0%
0.
04
0=
#1920000000
1!
1%
b00001000 ,
1.
14
b00000011 ;
1=
#1930000000
0!
0%
0.
04
0=
#1940000000
1!
1%
b00001001 ,
1.
14
b00000100 ;
1=
#1950000000
0!
0%
0.
04
0=
#1960000000
1!
1%
b00001010 ,
1.
14
b00000101 ;
1=
#1970000000
0!
0%
0.
04
0=
#1980000000
1!
1%
1)
b00000000 ,
b00001000 -
1.
12
14
b00000110 ;
1=
#1990000000
0!
0%
0.
04
0=
#2000000000
1!
1%
0+
b00000001 ,
1.
00
14
b00000111 ;
1=
#2010000000
0!
0%
0.
04
0=
#2020000000
1!
1%
b00000010 ,
1.
14
b00001000 ;
1=
#2030000000
0!
0%
0.
04
0=
#2040000000
1!
1%
b00000011 ,
1.
14
b00001001 ;
1=
#2050000000
0!
0%
0.
04
0=
#2060000000
1!
1%
b00000100 ,
1.
14
b00001010 ;
1=
#2070000000
0!
0%
0.
04
0=
#2080000000
1!
1%
b00000101 ,
1.
14
b00000000 ;
b00001000 <
1=
#2090000000
0!
0%
0.
04
0=
#2100000000
1!
1%
b00000110 ,
1.
14
1=
#2110000000
0!
0%
0.
04
0=
#2120000000
1!
1%
b00000111 ,
1.
14
b00000001 ;
1=
#2130000000
0!
0%
0.
04
0=
#2140000000
1!
1%
b00001000 ,
1.
14
b00000010 ;
1=
#2150000000
0!
0%
0.
04
0=
#2160000000
1!
1%
b00001001 ,
1.
14
b00000011 ;
1=
#2170000000
0!
0%
0.
04
0=
#2180000000
1!
1%
b00001010 ,
1.
14
b00000100 ;
1=
#2190000000
0!
0%
0.
04
0=
#2200000000
1!
1%
b00001011 ,
1.
14
b00000101 ;
1=
#2210000000
0!
0%
0.
04
0=
#2220000000
1!
1#
1%
1.
14
1:
b00000000 ;
1=
